{
    "A033RC0A144NBEA": {
        "title": "National income: Compensation of employees (DISCONTINUED)",
        "start": "1929-01-01",
        "end": "2016-01-01",
        "frequency": "Annual",
        "units": "Millions of Dollars",
        "popularity": 1
    },
    "A033RC1A027NBEA": {
        "title": "National income: Compensation of employees",
        "start": "1929-01-01",
        "end": "2021-01-01",
        "frequency": "Annual",
        "units": "Billions of Dollars",
        "popularity": 26
    },
    "A038RC1A027NBEA": {
        "title": "Compensation of employees: Supplements to wages and salaries",
        "start": "1929-01-01",
        "end": "2021-01-01",
        "frequency": "Annual",
        "units": "Billions of Dollars",
        "popularity": 1
    },
    "A038RC1Q027SBEA": {
        "title": "Compensation of employees: Supplements to wages and salaries",
        "start": "1947-01-01",
        "end": "2022-07-01",
        "frequency": "Quarterly",
        "units": "Billions of Dollars",
        "popularity": 11
    },
    "A1642C1A027NBEA": {
        "title": "National income: Domestic business: Noncorporate business: Sole proprietorships and partnerships: Compensation of employees",
        "start": "1948-01-01",
        "end": "2021-01-01",
        "frequency": "Annual",
        "units": "Billions of Dollars",
        "popularity": 1
    },
    "A1651C1A027NBEA": {
        "title": "National income: Domestic business: Noncorporate business: Other private business: Compensation of employees",
        "start": "1948-01-01",
        "end": "2021-01-01",
        "frequency": "Annual",
        "units": "Billions of Dollars",
        "popularity": 1
    },
    "A1658C1A027NBEA": {
        "title": "National income: Domestic business: Noncorporate business: Government enterprises: Compensation of employees",
        "start": "1948-01-01",
        "end": "2021-01-01",
        "frequency": "Annual",
        "units": "Billions of Dollars",
        "popularity": 1
    },
    "A4002C0A144NBEA": {
        "title": "Gross Domestic Income: Compensation of Employees, Paid (DISCONTINUED)",
        "start": "1929-01-01",
        "end": "2016-01-01",
        "frequency": "Annual",
        "units": "Millions of Dollars",
        "popularity": 1
    },
    "A4003C0A144NBEA": {
        "title": "Compensation of employees: Domestic private industries",
        "start": "1929-01-01",
        "end": "2021-01-01",
        "frequency": "Annual",
        "units": "Millions of Dollars",
        "popularity": 1
    },
    "A4004C0A144NBEA": {
        "title": "Compensation of employees: Domestic private industries: Agriculture, forestry, and fishing",
        "start": "1987-01-01",
        "end": "2000-01-01",
        "frequency": "Annual",
        "units": "Millions of Dollars",
        "popularity": 1
    },
    "A4007C0A144NBEA": {
        "title": "Compensation of employees: Domestic private industries: Mining",
        "start": "1987-01-01",
        "end": "2000-01-01",
        "frequency": "Annual",
        "units": "Millions of Dollars",
        "popularity": 0
    },
    "A4013C0A144NBEA": {
        "title": "Compensation of employees: Domestic private industries: Manufacturing",
        "start": "1987-01-01",
        "end": "2000-01-01",
        "frequency": "Annual",
        "units": "Millions of Dollars",
        "popularity": 1
    },
    "A4014C0A144NBEA": {
        "title": "Compensation of employees: Domestic private industries: Manufacturing: Durable goods",
        "start": "1987-01-01",
        "end": "2000-01-01",
        "frequency": "Annual",
        "units": "Millions of Dollars",
        "popularity": 1
    },
    "A4026C0A144NBEA": {
        "title": "Compensation of employees: Domestic private industries: Manufacturing: Nondurable goods",
        "start": "1987-01-01",
        "end": "2000-01-01",
        "frequency": "Annual",
        "units": "Millions of Dollars",
        "popularity": 0
    },
    "A4037C0A144NBEA": {
        "title": "Compensation of employees: Domestic private industries: Transportation and public utilities",
        "start": "1929-01-01",
        "end": "1948-01-01",
        "frequency": "Annual",
        "units": "Millions of Dollars",
        "popularity": 1
    },
    "A4038C0A144NBEA": {
        "title": "Compensation of employees: Domestic private industries: Transportation",
        "start": "1929-01-01",
        "end": "1948-01-01",
        "frequency": "Annual",
        "units": "Millions of Dollars",
        "popularity": 1
    },
    "A4046C0A144NBEA": {
        "title": "Compensation of employees: Domestic private industries: Communication",
        "start": "1929-01-01",
        "end": "1948-01-01",
        "frequency": "Annual",
        "units": "Millions of Dollars",
        "popularity": 1
    },
    "A4052C0A144NBEA": {
        "title": "Compensation of employees: Domestic private industries: Finance, insurance, and real estate",
        "start": "1987-01-01",
        "end": "2000-01-01",
        "frequency": "Annual",
        "units": "Millions of Dollars",
        "popularity": 1
    },
    "A4060C0A144NBEA": {
        "title": "Compensation of employees: Domestic private industries: Services",
        "start": "1987-01-01",
        "end": "2000-01-01",
        "frequency": "Annual",
        "units": "Millions of Dollars",
        "popularity": 1
    },
    "A4071C0A144NBEA": {
        "title": "Compensation of employees: Domestic private industries: Social services and membership organizations",
        "start": "1987-01-01",
        "end": "2000-01-01",
        "frequency": "Annual",
        "units": "Millions of Dollars",
        "popularity": 1
    },
    "A4076C0A144NBEA": {
        "title": "Compensation of employees: Government",
        "start": "1929-01-01",
        "end": "2021-01-01",
        "frequency": "Annual",
        "units": "Millions of Dollars",
        "popularity": 1
    },
    "A4081C0A144NBEA": {
        "title": "Compensation of employees: Federal government enterprises",
        "start": "1929-01-01",
        "end": "2021-01-01",
        "frequency": "Annual",
        "units": "Millions of Dollars",
        "popularity": 1
    },
    "A4087C0A144NBEA": {
        "title": "Compensation of employees: Rest of the world (DISCONTINUED)",
        "start": "1929-01-01",
        "end": "1969-01-01",
        "frequency": "Annual",
        "units": "Millions of Dollars",
        "popularity": 1
    },
    "A4091C0A144NBEA": {
        "title": "Compensation of employees: Nonfarm business",
        "start": "1929-01-01",
        "end": "2000-01-01",
        "frequency": "Annual",
        "units": "Millions of Dollars",
        "popularity": 1
    },
    "A4187C0A144NBEA": {
        "title": "National income: Rest of the world: Compensation of employees (DISCONTINUED)",
        "start": "1929-01-01",
        "end": "2016-01-01",
        "frequency": "Annual",
        "units": "Millions of Dollars",
        "popularity": 1
    },
    "A4187C1A027NBEA": {
        "title": "National income: Rest of the world: Compensation of employees",
        "start": "1929-01-01",
        "end": "2021-01-01",
        "frequency": "Annual",
        "units": "Billions of Dollars",
        "popularity": 1
    },
    "A442RC1A027NBEA": {
        "title": "National income: Domestic business: Corporate business: Compensation of employees",
        "start": "1929-01-01",
        "end": "2021-01-01",
        "frequency": "Annual",
        "units": "Billions of Dollars",
        "popularity": 1
    },
    "A442RC1Q027SBEA": {
        "title": "Net value added of corporate business: Compensation of employees",
        "start": "1947-01-01",
        "end": "2022-07-01",
        "frequency": "Quarterly",
        "units": "Billions of Dollars",
        "popularity": 5
    },
    "A444RC1A027NBEA": {
        "title": "National income: Domestic business: Corporate business: Compensation of employees: Supplements to wages and salaries",
        "start": "1929-01-01",
        "end": "2021-01-01",
        "frequency": "Annual",
        "units": "Billions of Dollars",
        "popularity": 1
    },
    "A444RC1Q027SBEA": {
        "title": "Net value added of corporate business: Compensation of employees: Supplements to wages and salaries",
        "start": "1947-01-01",
        "end": "2022-07-01",
        "frequency": "Quarterly",
        "units": "Billions of Dollars",
        "popularity": 1
    },
    "B1644C1A027NBEA": {
        "title": "National income: Domestic business: Noncorporate business: Sole proprietorships and partnerships: Compensation of employees: Supplements to wages and salaries",
        "start": "1948-01-01",
        "end": "2021-01-01",
        "frequency": "Annual",
        "units": "Billions of Dollars",
        "popularity": 1
    },
    "B1653C1A027NBEA": {
        "title": "National income: Domestic business: Noncorporate business: Other private business: Compensation of employees: Supplements to wages and salaries",
        "start": "1948-01-01",
        "end": "2021-01-01",
        "frequency": "Annual",
        "units": "Billions of Dollars",
        "popularity": 1
    },
    "B1660C1A027NBEA": {
        "title": "National income: Domestic business: Noncorporate business: Government enterprises: Compensation of employees: Supplements to wages and salaries",
        "start": "1948-01-01",
        "end": "2021-01-01",
        "frequency": "Annual",
        "units": "Billions of Dollars",
        "popularity": 1
    },
    "B1662C1A027NBEA": {
        "title": "National income: Households: Compensation of employees: Supplements to wages and salaries",
        "start": "1948-01-01",
        "end": "2021-01-01",
        "frequency": "Annual",
        "units": "Billions of Dollars",
        "popularity": 1
    },
    "B1664C1A027NBEA": {
        "title": "National income: General government: Compensation of employees: Supplements to wages and salaries",
        "start": "1948-01-01",
        "end": "2021-01-01",
        "frequency": "Annual",
        "units": "Billions of Dollars",
        "popularity": 1
    },
    "B251RC0A144NBEA": {
        "title": "Net value added: Net domestic product: General government: State and local (DISCONTINUED)",
        "start": "1929-01-01",
        "end": "2016-01-01",
        "frequency": "Annual",
        "units": "Millions of Dollars",
        "popularity": 1
    },
    "B4005C0A144NBEA": {
        "title": "Compensation of employees: Domestic private industries: Farms",
        "start": "1987-01-01",
        "end": "2000-01-01",
        "frequency": "Annual",
        "units": "Millions of Dollars",
        "popularity": 1
    },
    "B4006C0A144NBEA": {
        "title": "Compensation of employees: Domestic private industries: Agricultural services, forestry, and fishing",
        "start": "1987-01-01",
        "end": "2000-01-01",
        "frequency": "Annual",
        "units": "Millions of Dollars",
        "popularity": 1
    },
    "B4008C0A144NBEA": {
        "title": "Compensation of employees: Domestic private industries: Metal mining",
        "start": "1929-01-01",
        "end": "1948-01-01",
        "frequency": "Annual",
        "units": "Millions of Dollars",
        "popularity": 1
    },
    "B4009C0A144NBEA": {
        "title": "Compensation of employees: Domestic private industries: Coal mining",
        "start": "1987-01-01",
        "end": "2000-01-01",
        "frequency": "Annual",
        "units": "Millions of Dollars",
        "popularity": 1
    },
    "B4010C0A144NBEA": {
        "title": "Compensation of employees: Domestic private industries: Oil and gas extraction",
        "start": "1987-01-01",
        "end": "2000-01-01",
        "frequency": "Annual",
        "units": "Millions of Dollars",
        "popularity": 1
    },
    "B4011C0A144NBEA": {
        "title": "Compensation of employees: Domestic private industries: Mining: Nonmetallic minerals, except fuels",
        "start": "1929-01-01",
        "end": "1948-01-01",
        "frequency": "Annual",
        "units": "Millions of Dollars",
        "popularity": 1
    },
    "B4012C0A144NBEA": {
        "title": "Compensation of employees: Domestic private industries: Construction",
        "start": "1987-01-01",
        "end": "2000-01-01",
        "frequency": "Annual",
        "units": "Millions of Dollars",
        "popularity": 1
    },
    "B4015C0A144NBEA": {
        "title": "Compensation of employees: Domestic private industries: Manufacturing: Durable goods: Lumber and wood products",
        "start": "1987-01-01",
        "end": "2000-01-01",
        "frequency": "Annual",
        "units": "Millions of Dollars",
        "popularity": 1
    },
    "B4016C0A144NBEA": {
        "title": "Compensation of employees: Domestic private industries: Manufacturing: Durable goods: Furniture and fixtures",
        "start": "1987-01-01",
        "end": "2000-01-01",
        "frequency": "Annual",
        "units": "Millions of Dollars",
        "popularity": 1
    },
    "B4017C0A144NBEA": {
        "title": "Compensation of employees: Domestic private industries: Manufacturing: Durable goods: Stone, clay, and glass products",
        "start": "1987-01-01",
        "end": "2000-01-01",
        "frequency": "Annual",
        "units": "Millions of Dollars",
        "popularity": 0
    },
    "B4018C0A144NBEA": {
        "title": "Compensation of employees: Domestic private industries: Manufacturing: Durable goods: Primary metal industries",
        "start": "1987-01-01",
        "end": "2000-01-01",
        "frequency": "Annual",
        "units": "Millions of Dollars",
        "popularity": 0
    },
    "B4019C0A144NBEA": {
        "title": "Compensation of employees: Domestic private industries: Manufacturing: Durable goods: Fabricated metal products",
        "start": "1987-01-01",
        "end": "2000-01-01",
        "frequency": "Annual",
        "units": "Millions of Dollars",
        "popularity": 0
    },
    "B4020C0A144NBEA": {
        "title": "Compensation of employees: Domestic private industries: Manufacturing: Durable goods: Machinery, except electrical",
        "start": "1987-01-01",
        "end": "2000-01-01",
        "frequency": "Annual",
        "units": "Millions of Dollars",
        "popularity": 1
    },
    "B4021C0A144NBEA": {
        "title": "Compensation of employees: Domestic private industries: Manufacturing: Durable goods: Electric and electronic equipment",
        "start": "1987-01-01",
        "end": "2000-01-01",
        "frequency": "Annual",
        "units": "Millions of Dollars",
        "popularity": 1
    },
    "B4022C0A144NBEA": {
        "title": "Compensation of employees: Domestic private industries: Manufacturing: Durable goods: Motor vehicles and equipment",
        "start": "1987-01-01",
        "end": "2000-01-01",
        "frequency": "Annual",
        "units": "Millions of Dollars",
        "popularity": 0
    },
    "B4023C0A144NBEA": {
        "title": "Compensation of employees: Domestic private industries: Manufacturing: Durable goods: Other transportation equipment",
        "start": "1987-01-01",
        "end": "2000-01-01",
        "frequency": "Annual",
        "units": "Millions of Dollars",
        "popularity": 0
    },
    "B4024C0A144NBEA": {
        "title": "Compensation of employees: Domestic private industries: Manufacturing: Durable goods: Instruments and related products",
        "start": "1987-01-01",
        "end": "2000-01-01",
        "frequency": "Annual",
        "units": "Millions of Dollars",
        "popularity": 1
    },
    "B4025C0A144NBEA": {
        "title": "Compensation of employees: Domestic private industries: Manufacturing: Durable goods: Miscellaneous manufacturing industries",
        "start": "1987-01-01",
        "end": "2000-01-01",
        "frequency": "Annual",
        "units": "Millions of Dollars",
        "popularity": 1
    },
    "B4027C0A144NBEA": {
        "title": "Compensation of employees: Domestic private industries: Manufacturing: Nondurable goods: Food and kindred products",
        "start": "1987-01-01",
        "end": "2000-01-01",
        "frequency": "Annual",
        "units": "Millions of Dollars",
        "popularity": 0
    },
    "B4028C0A144NBEA": {
        "title": "Compensation of employees: Domestic private industries: Manufacturing: Nondurable goods: Tobacco manufactures",
        "start": "1929-01-01",
        "end": "1948-01-01",
        "frequency": "Annual",
        "units": "Millions of Dollars",
        "popularity": 1
    },
    "B4029C0A144NBEA": {
        "title": "Compensation of employees: Domestic private industries: Manufacturing: Nondurable goods: Textile mill products",
        "start": "1987-01-01",
        "end": "2000-01-01",
        "frequency": "Annual",
        "units": "Millions of Dollars",
        "popularity": 0
    },
    "B4030C0A144NBEA": {
        "title": "Compensation of employees: Domestic private industries: Manufacturing: Nondurable goods: Apparel and other textile products",
        "start": "1987-01-01",
        "end": "2000-01-01",
        "frequency": "Annual",
        "units": "Millions of Dollars",
        "popularity": 1
    },
    "B4031C0A144NBEA": {
        "title": "Compensation of employees: Domestic private industries: Manufacturing: Nondurable goods: Paper and allied products",
        "start": "1929-01-01",
        "end": "1948-01-01",
        "frequency": "Annual",
        "units": "Millions of Dollars",
        "popularity": 1
    },
    "B4032C0A144NBEA": {
        "title": "Compensation of employees: Domestic private industries: Manufacturing: Nondurable goods: Printing and publishing",
        "start": "1987-01-01",
        "end": "2000-01-01",
        "frequency": "Annual",
        "units": "Millions of Dollars",
        "popularity": 0
    },
    "B4033C0A144NBEA": {
        "title": "Compensation of employees: Domestic private industries: Manufacturing: Nondurable goods: Chemicals and allied products",
        "start": "1987-01-01",
        "end": "2000-01-01",
        "frequency": "Annual",
        "units": "Millions of Dollars",
        "popularity": 0
    },
    "B4034C0A144NBEA": {
        "title": "Compensation of employees: Domestic private industries: Manufacturing: Nondurable goods: Petroleum and coal products",
        "start": "1987-01-01",
        "end": "2000-01-01",
        "frequency": "Annual",
        "units": "Millions of Dollars",
        "popularity": 1
    },
    "B4035C0A144NBEA": {
        "title": "Compensation of employees: Domestic private industries: Manufacturing: Nondurable goods: Rubber and miscellaneous plastics products",
        "start": "1987-01-01",
        "end": "2000-01-01",
        "frequency": "Annual",
        "units": "Millions of Dollars",
        "popularity": 1
    },
    "B4036C0A144NBEA": {
        "title": "Compensation of employees: Domestic private industries: Manufacturing: Nondurable goods: Leather and leather products",
        "start": "1987-01-01",
        "end": "2000-01-01",
        "frequency": "Annual",
        "units": "Millions of Dollars",
        "popularity": 0
    },
    "B4039C0A144NBEA": {
        "title": "Compensation of employees: Domestic private industries: Railroad transportation",
        "start": "1929-01-01",
        "end": "1948-01-01",
        "frequency": "Annual",
        "units": "Millions of Dollars",
        "popularity": 1
    },
    "B4040C0A144NBEA": {
        "title": "Compensation of employees: Domestic private industries: Transportation: Local and interurban passenger transit",
        "start": "1987-01-01",
        "end": "2000-01-01",
        "frequency": "Annual",
        "units": "Millions of Dollars",
        "popularity": 1
    },
    "B4041C0A144NBEA": {
        "title": "Compensation of employees: Domestic private industries: Transportation: Trucking and warehousing",
        "start": "1929-01-01",
        "end": "1948-01-01",
        "frequency": "Annual",
        "units": "Millions of Dollars",
        "popularity": 1
    },
    "B4042C0A144NBEA": {
        "title": "Compensation of employees: Domestic private industries: Water transportation",
        "start": "1987-01-01",
        "end": "2000-01-01",
        "frequency": "Annual",
        "units": "Millions of Dollars",
        "popularity": 1
    },
    "B4043C0A144NBEA": {
        "title": "Compensation of employees: Domestic private industries: Transportation by air",
        "start": "1987-01-01",
        "end": "2000-01-01",
        "frequency": "Annual",
        "units": "Millions of Dollars",
        "popularity": 1
    },
    "B4044C0A144NBEA": {
        "title": "Compensation of employees: Domestic private industries: Transportation: Pipelines, except natural gas",
        "start": "1929-01-01",
        "end": "1948-01-01",
        "frequency": "Annual",
        "units": "Millions of Dollars",
        "popularity": 1
    },
    "B4045C0A144NBEA": {
        "title": "Compensation of employees: Domestic private industries: Transportation services",
        "start": "1987-01-01",
        "end": "2000-01-01",
        "frequency": "Annual",
        "units": "Millions of Dollars",
        "popularity": 1
    },
    "B4047C0A144NBEA": {
        "title": "Compensation of employees: Domestic private industries: Communication: Telephone and telegraph",
        "start": "1929-01-01",
        "end": "1948-01-01",
        "frequency": "Annual",
        "units": "Millions of Dollars",
        "popularity": 1
    },
    "B4048C0A144NBEA": {
        "title": "Compensation of employees: Domestic private industries: Communication: Radio and television",
        "start": "1929-01-01",
        "end": "1948-01-01",
        "frequency": "Annual",
        "units": "Millions of Dollars",
        "popularity": 1
    },
    "B4049C0A144NBEA": {
        "title": "Compensation of employees: Domestic private industries: Transportation and public utilities: Electric, gas, and sanitary services",
        "start": "1929-01-01",
        "end": "1948-01-01",
        "frequency": "Annual",
        "units": "Millions of Dollars",
        "popularity": 0
    },
    "B4050C0A144NBEA": {
        "title": "Compensation of employees: Domestic private industries: Wholesale trade",
        "start": "1987-01-01",
        "end": "2000-01-01",
        "frequency": "Annual",
        "units": "Millions of Dollars",
        "popularity": 0
    },
    "B4051C0A144NBEA": {
        "title": "Compensation of employees: Domestic private industries: Retail trade",
        "start": "1987-01-01",
        "end": "2000-01-01",
        "frequency": "Annual",
        "units": "Millions of Dollars",
        "popularity": 1
    },
    "B4053C0A144NBEA": {
        "title": "Compensation of employees: Domestic private industries: Depository institutions",
        "start": "1929-01-01",
        "end": "1948-01-01",
        "frequency": "Annual",
        "units": "Millions of Dollars",
        "popularity": 1
    },
    "B4054C0A144NBEA": {
        "title": "Compensation of employees: Domestic private industries: Nondepository institutions",
        "start": "1987-01-01",
        "end": "2000-01-01",
        "frequency": "Annual",
        "units": "Millions of Dollars",
        "popularity": 1
    },
    "B4055C0A144NBEA": {
        "title": "Compensation of employees: Domestic private industries: Security and commodity brokers",
        "start": "1987-01-01",
        "end": "2000-01-01",
        "frequency": "Annual",
        "units": "Millions of Dollars",
        "popularity": 1
    },
    "B4056C0A144NBEA": {
        "title": "Compensation of employees: Domestic private industries: Insurance carriers",
        "start": "1929-01-01",
        "end": "1948-01-01",
        "frequency": "Annual",
        "units": "Millions of Dollars",
        "popularity": 1
    },
    "B4057C0A144NBEA": {
        "title": "Compensation of employees: Domestic private industries: Insurance agents, brokers, and service",
        "start": "1987-01-01",
        "end": "2000-01-01",
        "frequency": "Annual",
        "units": "Millions of Dollars",
        "popularity": 1
    },
    "B4058C0A144NBEA": {
        "title": "Compensation of employees: Domestic private industries: Real estate",
        "start": "1987-01-01",
        "end": "2000-01-01",
        "frequency": "Annual",
        "units": "Millions of Dollars",
        "popularity": 1
    },
    "B4059C0A144NBEA": {
        "title": "Compensation of employees: Domestic private industries: Holding and other investment offices",
        "start": "1987-01-01",
        "end": "2000-01-01",
        "frequency": "Annual",
        "units": "Millions of Dollars",
        "popularity": 1
    },
    "B4061C0A144NBEA": {
        "title": "Compensation of employees: Domestic private industries: Services: Hotels and other lodging places",
        "start": "1929-01-01",
        "end": "1948-01-01",
        "frequency": "Annual",
        "units": "Millions of Dollars",
        "popularity": 1
    },
    "B4062C0A144NBEA": {
        "title": "Compensation of employees: Domestic private industries: Personal services",
        "start": "1929-01-01",
        "end": "1948-01-01",
        "frequency": "Annual",
        "units": "Millions of Dollars",
        "popularity": 1
    },
    "B4063C0A144NBEA": {
        "title": "Compensation of employees: Domestic private industries: Business services",
        "start": "1987-01-01",
        "end": "2000-01-01",
        "frequency": "Annual",
        "units": "Millions of Dollars",
        "popularity": 1
    },
    "B4064C0A144NBEA": {
        "title": "Compensation of employees: Domestic private industries: Auto repair, services, and parking",
        "start": "1987-01-01",
        "end": "2000-01-01",
        "frequency": "Annual",
        "units": "Millions of Dollars",
        "popularity": 1
    },
    "B4065C0A144NBEA": {
        "title": "Compensation of employees: Domestic private industries: Miscellaneous repair services",
        "start": "1929-01-01",
        "end": "1948-01-01",
        "frequency": "Annual",
        "units": "Millions of Dollars",
        "popularity": 1
    },
    "B4066C0A144NBEA": {
        "title": "Compensation of employees: Domestic private industries: Services: Motion pictures",
        "start": "1929-01-01",
        "end": "1948-01-01",
        "frequency": "Annual",
        "units": "Millions of Dollars",
        "popularity": 0
    },
    "B4067C0A144NBEA": {
        "title": "Compensation of employees: Domestic private industries: Amusement and recreation services",
        "start": "1929-01-01",
        "end": "1948-01-01",
        "frequency": "Annual",
        "units": "Millions of Dollars",
        "popularity": 1
    },
    "B4068C0A144NBEA": {
        "title": "Compensation of employees: Domestic private industries: Health services",
        "start": "1987-01-01",
        "end": "2000-01-01",
        "frequency": "Annual",
        "units": "Millions of Dollars",
        "popularity": 1
    },
    "B4069C0A144NBEA": {
        "title": "Compensation of employees: Domestic private industries: Legal services",
        "start": "1929-01-01",
        "end": "1948-01-01",
        "frequency": "Annual",
        "units": "Millions of Dollars",
        "popularity": 1
    },
    "B4070C0A144NBEA": {
        "title": "Compensation of employees: Domestic private industries: Educational services",
        "start": "1987-01-01",
        "end": "2000-01-01",
        "frequency": "Annual",
        "units": "Millions of Dollars",
        "popularity": 1
    },
    "B4072C0A144NBEA": {
        "title": "Compensation of employees: Domestic private industries: Social services",
        "start": "1987-01-01",
        "end": "2000-01-01",
        "frequency": "Annual",
        "units": "Millions of Dollars",
        "popularity": 0
    },
    "B4073C0A144NBEA": {
        "title": "Compensation of employees: Domestic private industries: Membership organizations",
        "start": "1987-01-01",
        "end": "2000-01-01",
        "frequency": "Annual",
        "units": "Millions of Dollars",
        "popularity": 1
    },
    "B4074C0A144NBEA": {
        "title": "Compensation of employees: Domestic private industries: Miscellaneous professional services",
        "start": "1987-01-01",
        "end": "2000-01-01",
        "frequency": "Annual",
        "units": "Millions of Dollars",
        "popularity": 1
    },
    "B4077C0A144NBEA": {
        "title": "Compensation of employees: Federal government",
        "start": "1929-01-01",
        "end": "2021-01-01",
        "frequency": "Annual",
        "units": "Millions of Dollars",
        "popularity": 1
    },
    "B4079C0A144NBEA": {
        "title": "Compensation of employees: Federal general government: Civilian",
        "start": "1948-01-01",
        "end": "2021-01-01",
        "frequency": "Annual",
        "units": "Millions of Dollars",
        "popularity": 1
    },
    "B4082C0A144NBEA": {
        "title": "Compensation of employees: State and local government",
        "start": "1929-01-01",
        "end": "2021-01-01",
        "frequency": "Annual",
        "units": "Millions of Dollars",
        "popularity": 1
    },
    "B4084C0A144NBEA": {
        "title": "Compensation of employees: State and local general government: Education",
        "start": "1952-01-01",
        "end": "2021-01-01",
        "frequency": "Annual",
        "units": "Millions of Dollars",
        "popularity": 1
    },
    "B4085C0A144NBEA": {
        "title": "Compensation of employees: State and local general government: Other",
        "start": "1952-01-01",
        "end": "2021-01-01",
        "frequency": "Annual",
        "units": "Millions of Dollars",
        "popularity": 1
    },
    "B4086C0A144NBEA": {
        "title": "Compensation of employees: State and local government enterprises",
        "start": "1929-01-01",
        "end": "2021-01-01",
        "frequency": "Annual",
        "units": "Millions of Dollars",
        "popularity": 1
    },
    "B4092C0A144NBEA": {
        "title": "Compensation of employees: Domestic private industries: Anthracite mining",
        "start": "1929-01-01",
        "end": "1948-01-01",
        "frequency": "Annual",
        "units": "Millions of Dollars",
        "popularity": 1
    },
    "B4093C0A144NBEA": {
        "title": "Compensation of employees: Domestic private industries: Utilities: electric and gas",
        "start": "1929-01-01",
        "end": "1947-01-01",
        "frequency": "Annual",
        "units": "Millions of Dollars",
        "popularity": 1
    },
    "B4094C0A144NBEA": {
        "title": "Compensation of employees: Domestic private industries: Local utilities and public services, n.e.c.",
        "start": "1929-01-01",
        "end": "1947-01-01",
        "frequency": "Annual",
        "units": "Millions of Dollars",
        "popularity": 1
    },
    "B4095C0A144NBEA": {
        "title": "Compensation of employees: Domestic private industries: Services: Commercial and trade schools and employment agencies",
        "start": "1929-01-01",
        "end": "1947-01-01",
        "frequency": "Annual",
        "units": "Millions of Dollars",
        "popularity": 1
    },
    "B4188C0A144NBEA": {
        "title": "Current receipts from the rest of the world: Income receipts: Wage and salary receipts (DISCONTINUED)",
        "start": "1959-01-01",
        "end": "2016-01-01",
        "frequency": "Annual",
        "units": "Millions of Dollars",
        "popularity": 1
    },
    "B4189C0A144NBEA": {
        "title": "Current payments to the rest of the world: Income payments: Wage and salary payments (DISCONTINUED)",
        "start": "1959-01-01",
        "end": "2016-01-01",
        "frequency": "Annual",
        "units": "Millions of Dollars",
        "popularity": 1
    },
    "B568RC0A144NBEA": {
        "title": "Net value added: Net domestic product: General government: Federal (DISCONTINUED)",
        "start": "1929-01-01",
        "end": "2016-01-01",
        "frequency": "Annual",
        "units": "Millions of Dollars",
        "popularity": 1
    },
    "C4091C0A144NBEA": {
        "title": "Compensation of employees: Nonfarm business (DISCONTINUED)",
        "start": "1929-01-01",
        "end": "1969-01-01",
        "frequency": "Annual",
        "units": "Millions of Dollars",
        "popularity": 1
    },
    "H4004C0A144NBEA": {
        "title": "Compensation of employees: Domestic private industries: Agriculture, forestry, and fisheries",
        "start": "1929-01-01",
        "end": "1948-01-01",
        "frequency": "Annual",
        "units": "Millions of Dollars",
        "popularity": 1
    },
    "H4005C0A144NBEA": {
        "title": "Compensation of employees: Domestic private industries: Farms",
        "start": "1929-01-01",
        "end": "1948-01-01",
        "frequency": "Annual",
        "units": "Millions of Dollars",
        "popularity": 1
    },
    "H4006C0A144NBEA": {
        "title": "Compensation of employees: Domestic private industries: Agricultural services, forestry, and fisheries",
        "start": "1929-01-01",
        "end": "1948-01-01",
        "frequency": "Annual",
        "units": "Millions of Dollars",
        "popularity": 1
    },
    "H4007C0A144NBEA": {
        "title": "Compensation of employees: Domestic private industries: Mining",
        "start": "1929-01-01",
        "end": "1948-01-01",
        "frequency": "Annual",
        "units": "Millions of Dollars",
        "popularity": 1
    },
    "H4009C0A144NBEA": {
        "title": "Compensation of employees: Domestic private industries: Bituminous and other soft coal mining",
        "start": "1929-01-01",
        "end": "1947-01-01",
        "frequency": "Annual",
        "units": "Millions of Dollars",
        "popularity": 1
    },
    "H4010C0A144NBEA": {
        "title": "Compensation of employees: Domestic private industries: Mining: Crude petroleum and natural gas",
        "start": "1929-01-01",
        "end": "1948-01-01",
        "frequency": "Annual",
        "units": "Millions of Dollars",
        "popularity": 1
    },
    "H4012C0A144NBEA": {
        "title": "Compensation of employees: Domestic private industries: Contract construction",
        "start": "1929-01-01",
        "end": "1948-01-01",
        "frequency": "Annual",
        "units": "Millions of Dollars",
        "popularity": 1
    },
    "H4013C0A144NBEA": {
        "title": "Compensation of employees: Domestic private industries: Manufacturing",
        "start": "1929-01-01",
        "end": "1948-01-01",
        "frequency": "Annual",
        "units": "Millions of Dollars",
        "popularity": 1
    },
    "H4014C0A144NBEA": {
        "title": "Compensation of employees: Domestic private industries: Manufacturing: Durable goods",
        "start": "1929-01-01",
        "end": "1948-01-01",
        "frequency": "Annual",
        "units": "Millions of Dollars",
        "popularity": 1
    },
    "H4015C0A144NBEA": {
        "title": "Compensation of employees: Domestic private industries: Manufacturing: Durable goods: Lumber and basic timber products",
        "start": "1929-01-01",
        "end": "1948-01-01",
        "frequency": "Annual",
        "units": "Millions of Dollars",
        "popularity": 1
    },
    "H4016C0A144NBEA": {
        "title": "Compensation of employees: Domestic private industries: Manufacturing: Durable goods: Furniture and finished lumber products",
        "start": "1929-01-01",
        "end": "1947-01-01",
        "frequency": "Annual",
        "units": "Millions of Dollars",
        "popularity": 1
    },
    "H4017C0A144NBEA": {
        "title": "Compensation of employees: Domestic private industries: Manufacturing: Durable goods: Stone, clay, and glass products",
        "start": "1929-01-01",
        "end": "1948-01-01",
        "frequency": "Annual",
        "units": "Millions of Dollars",
        "popularity": 1
    },
    "H4018C0A144NBEA": {
        "title": "Compensation of employees: Domestic private industries: Manufacturing: Durable goods: Iron and steel and their products, including ordnance",
        "start": "1929-01-01",
        "end": "1948-01-01",
        "frequency": "Annual",
        "units": "Millions of Dollars",
        "popularity": 1
    },
    "H4019C0A144NBEA": {
        "title": "Compensation of employees: Domestic private industries: Manufacturing: Durable goods: Nonferrous metals and their products",
        "start": "1929-01-01",
        "end": "1947-01-01",
        "frequency": "Annual",
        "units": "Millions of Dollars",
        "popularity": 1
    },
    "H4020C0A144NBEA": {
        "title": "Compensation of employees: Domestic private industries: Manufacturing: Durable goods: Machinery, except electrical",
        "start": "1929-01-01",
        "end": "1948-01-01",
        "frequency": "Annual",
        "units": "Millions of Dollars",
        "popularity": 1
    },
    "H4021C0A144NBEA": {
        "title": "Compensation of employees: Domestic private industries: Manufacturing: Durable goods: Electric and electronic equipment",
        "start": "1929-01-01",
        "end": "1948-01-01",
        "frequency": "Annual",
        "units": "Millions of Dollars",
        "popularity": 0
    },
    "H4022C0A144NBEA": {
        "title": "Compensation of employees: Domestic private industries: Manufacturing: Durable goods: Motor vehicles and equipment",
        "start": "1929-01-01",
        "end": "1948-01-01",
        "frequency": "Annual",
        "units": "Millions of Dollars",
        "popularity": 1
    },
    "H4023C0A144NBEA": {
        "title": "Compensation of employees: Domestic private industries: Manufacturing: Durable goods: Other transportation equipment",
        "start": "1929-01-01",
        "end": "1947-01-01",
        "frequency": "Annual",
        "units": "Millions of Dollars",
        "popularity": 0
    },
    "H4025C0A144NBEA": {
        "title": "Compensation of employees: Domestic private industries: Manufacturing: Durable goods: Miscellaneous manufacturing, including instruments and miscellaneous plastic products",
        "start": "1929-01-01",
        "end": "1947-01-01",
        "frequency": "Annual",
        "units": "Millions of Dollars",
        "popularity": 1
    },
    "H4026C0A144NBEA": {
        "title": "Compensation of employees: Domestic private industries: Manufacturing: Nondurable goods",
        "start": "1929-01-01",
        "end": "1948-01-01",
        "frequency": "Annual",
        "units": "Millions of Dollars",
        "popularity": 1
    },
    "H4027C0A144NBEA": {
        "title": "Compensation of employees: Domestic private industries: Manufacturing: Nondurable goods: Food and kindred products",
        "start": "1929-01-01",
        "end": "1948-01-01",
        "frequency": "Annual",
        "units": "Millions of Dollars",
        "popularity": 1
    },
    "H4029C0A144NBEA": {
        "title": "Compensation of employees: Domestic private industries: Manufacturing: Nondurable goods: Textile mill products",
        "start": "1929-01-01",
        "end": "1948-01-01",
        "frequency": "Annual",
        "units": "Millions of Dollars",
        "popularity": 1
    },
    "H4030C0A144NBEA": {
        "title": "Compensation of employees: Domestic private industries: Manufacturing: Nondurable goods: Apparel and other textile products",
        "start": "1929-01-01",
        "end": "1948-01-01",
        "frequency": "Annual",
        "units": "Millions of Dollars",
        "popularity": 1
    },
    "H4032C0A144NBEA": {
        "title": "Compensation of employees: Domestic private industries: Manufacturing: Nondurable goods: Printing and publishing",
        "start": "1929-01-01",
        "end": "1948-01-01",
        "frequency": "Annual",
        "units": "Millions of Dollars",
        "popularity": 1
    },
    "H4033C0A144NBEA": {
        "title": "Compensation of employees: Domestic private industries: Manufacturing: Nondurable goods: Chemicals and allied products",
        "start": "1929-01-01",
        "end": "1948-01-01",
        "frequency": "Annual",
        "units": "Millions of Dollars",
        "popularity": 1
    },
    "H4034C0A144NBEA": {
        "title": "Compensation of employees: Domestic private industries: Manufacturing: Nondurable goods: Petroleum and coal products",
        "start": "1929-01-01",
        "end": "1948-01-01",
        "frequency": "Annual",
        "units": "Millions of Dollars",
        "popularity": 1
    },
    "H4035C0A144NBEA": {
        "title": "Compensation of employees: Domestic private industries: Manufacturing: Nondurable goods: Rubber products",
        "start": "1929-01-01",
        "end": "1948-01-01",
        "frequency": "Annual",
        "units": "Millions of Dollars",
        "popularity": 1
    },
    "H4036C0A144NBEA": {
        "title": "Compensation of employees: Domestic private industries: Manufacturing: Nondurable goods: Leather and leather products",
        "start": "1929-01-01",
        "end": "1948-01-01",
        "frequency": "Annual",
        "units": "Millions of Dollars",
        "popularity": 1
    },
    "H4040C0A144NBEA": {
        "title": "Compensation of employees: Domestic private industries: Transportation: Local and interurban passenger transit",
        "start": "1929-01-01",
        "end": "1948-01-01",
        "frequency": "Annual",
        "units": "Millions of Dollars",
        "popularity": 1
    },
    "H4042C0A144NBEA": {
        "title": "Compensation of employees: Domestic private industries: Water transportation",
        "start": "1929-01-01",
        "end": "1948-01-01",
        "frequency": "Annual",
        "units": "Millions of Dollars",
        "popularity": 0
    },
    "H4043C0A144NBEA": {
        "title": "Compensation of employees: Domestic private industries: Transportation by air",
        "start": "1929-01-01",
        "end": "1948-01-01",
        "frequency": "Annual",
        "units": "Millions of Dollars",
        "popularity": 1
    },
    "H4045C0A144NBEA": {
        "title": "Compensation of employees: Domestic private industries: Transportation services",
        "start": "1929-01-01",
        "end": "1948-01-01",
        "frequency": "Annual",
        "units": "Millions of Dollars",
        "popularity": 0
    },
    "H4050C0A144NBEA": {
        "title": "Compensation of employees: Domestic private industries: Wholesale trade",
        "start": "1929-01-01",
        "end": "1948-01-01",
        "frequency": "Annual",
        "units": "Millions of Dollars",
        "popularity": 0
    },
    "H4051C0A144NBEA": {
        "title": "Compensation of employees: Domestic private industries: Retail trade and automobile services",
        "start": "1929-01-01",
        "end": "1948-01-01",
        "frequency": "Annual",
        "units": "Millions of Dollars",
        "popularity": 1
    },
    "H4052C0A144NBEA": {
        "title": "Compensation of employees: Domestic private industries: Finance, insurance, and real estate",
        "start": "1929-01-01",
        "end": "1948-01-01",
        "frequency": "Annual",
        "units": "Millions of Dollars",
        "popularity": 1
    },
    "H4054C0A144NBEA": {
        "title": "Compensation of employees: Domestic private industries: Credit agencies (other than banks) and holding and other investment companies",
        "start": "1929-01-01",
        "end": "1948-01-01",
        "frequency": "Annual",
        "units": "Millions of Dollars",
        "popularity": 1
    },
    "H4055C0A144NBEA": {
        "title": "Compensation of employees: Domestic private industries: Finance, insurance, and real estate: Security and commodity brokers, and services",
        "start": "1929-01-01",
        "end": "1948-01-01",
        "frequency": "Annual",
        "units": "Millions of Dollars",
        "popularity": 1
    },
    "H4057C0A144NBEA": {
        "title": "Compensation of employees: Domestic private industries: Insurance agents, brokers, and service",
        "start": "1929-01-01",
        "end": "1948-01-01",
        "frequency": "Annual",
        "units": "Millions of Dollars",
        "popularity": 1
    },
    "H4058C0A144NBEA": {
        "title": "Compensation of employees: Domestic private industries: Real estate",
        "start": "1929-01-01",
        "end": "1948-01-01",
        "frequency": "Annual",
        "units": "Millions of Dollars",
        "popularity": 1
    },
    "H4060C0A144NBEA": {
        "title": "Compensation of employees: Domestic private industries: Services",
        "start": "1929-01-01",
        "end": "1948-01-01",
        "frequency": "Annual",
        "units": "Millions of Dollars",
        "popularity": 1
    },
    "H4063C0A144NBEA": {
        "title": "Compensation of employees: Domestic private industries: Business services",
        "start": "1929-01-01",
        "end": "1948-01-01",
        "frequency": "Annual",
        "units": "Millions of Dollars",
        "popularity": 1
    },
    "H4068C0A144NBEA": {
        "title": "Compensation of employees: Domestic private industries: Health services",
        "start": "1929-01-01",
        "end": "1948-01-01",
        "frequency": "Annual",
        "units": "Millions of Dollars",
        "popularity": 1
    },
    "H4070C0A144NBEA": {
        "title": "Compensation of employees: Domestic private industries: Educational services, n.e.c.",
        "start": "1929-01-01",
        "end": "1948-01-01",
        "frequency": "Annual",
        "units": "Millions of Dollars",
        "popularity": 1
    },
    "H4071C0A144NBEA": {
        "title": "Compensation of employees: Domestic private industries: Services: Membership organizations",
        "start": "1929-01-01",
        "end": "1948-01-01",
        "frequency": "Annual",
        "units": "Millions of Dollars",
        "popularity": 0
    },
    "H4074C0A144NBEA": {
        "title": "Compensation of employees: Domestic private industries: Miscellaneous professional services",
        "start": "1929-01-01",
        "end": "1948-01-01",
        "frequency": "Annual",
        "units": "Millions of Dollars",
        "popularity": 0
    },
    "J4004C0A144NBEA": {
        "title": "Compensation of employees: Domestic private industries: Agriculture, forestry, and fishing (DISCONTINUED)",
        "start": "1948-01-01",
        "end": "1969-01-01",
        "frequency": "Annual",
        "units": "Millions of Dollars",
        "popularity": 1
    },
    "J4006C0A144NBEA": {
        "title": "Compensation of employees: Domestic private industries: Agricultural services, forestry, and fishing",
        "start": "1948-01-01",
        "end": "1987-01-01",
        "frequency": "Annual",
        "units": "Millions of Dollars",
        "popularity": 1
    },
    "J4007C0A144NBEA": {
        "title": "Compensation of employees: Domestic private industries: Mining (DISCONTINUED)",
        "start": "1948-01-01",
        "end": "1969-01-01",
        "frequency": "Annual",
        "units": "Millions of Dollars",
        "popularity": 1
    },
    "J4009C0A144NBEA": {
        "title": "Compensation of employees: Domestic private industries: Coal mining",
        "start": "1948-01-01",
        "end": "1987-01-01",
        "frequency": "Annual",
        "units": "Millions of Dollars",
        "popularity": 1
    },
    "J4010C0A144NBEA": {
        "title": "Compensation of employees: Domestic private industries: Oil and gas extraction",
        "start": "1948-01-01",
        "end": "1987-01-01",
        "frequency": "Annual",
        "units": "Millions of Dollars",
        "popularity": 1
    },
    "J4012C0A144NBEA": {
        "title": "Compensation of employees: Domestic private industries: Construction (DISCONTINUED)",
        "start": "1948-01-01",
        "end": "1969-01-01",
        "frequency": "Annual",
        "units": "Millions of Dollars",
        "popularity": 1
    },
    "J4013C0A144NBEA": {
        "title": "Compensation of employees: Domestic private industries: Manufacturing (DISCONTINUED)",
        "start": "1948-01-01",
        "end": "1969-01-01",
        "frequency": "Annual",
        "units": "Millions of Dollars",
        "popularity": 1
    },
    "J4014C0A144NBEA": {
        "title": "Compensation of employees: Domestic private industries: Manufacturing: Durable goods (DISCONTINUED)",
        "start": "1948-01-01",
        "end": "1969-01-01",
        "frequency": "Annual",
        "units": "Millions of Dollars",
        "popularity": 1
    },
    "J4015C0A144NBEA": {
        "title": "Compensation of employees: Domestic private industries: Manufacturing: Durable goods: Lumber and wood products",
        "start": "1948-01-01",
        "end": "1987-01-01",
        "frequency": "Annual",
        "units": "Millions of Dollars",
        "popularity": 0
    },
    "J4016C0A144NBEA": {
        "title": "Compensation of employees: Domestic private industries: Manufacturing: Durable goods: Furniture and fixtures",
        "start": "1948-01-01",
        "end": "1987-01-01",
        "frequency": "Annual",
        "units": "Millions of Dollars",
        "popularity": 0
    },
    "J4017C0A144NBEA": {
        "title": "Compensation of employees: Domestic private industries: Manufacturing: Durable goods: Stone, clay, and glass products",
        "start": "1948-01-01",
        "end": "1987-01-01",
        "frequency": "Annual",
        "units": "Millions of Dollars",
        "popularity": 0
    },
    "J4018C0A144NBEA": {
        "title": "Compensation of employees: Domestic private industries: Manufacturing: Durable goods: Primary metal industries",
        "start": "1948-01-01",
        "end": "1987-01-01",
        "frequency": "Annual",
        "units": "Millions of Dollars",
        "popularity": 1
    },
    "J4019C0A144NBEA": {
        "title": "Compensation of employees: Domestic private industries: Manufacturing: Durable goods: Fabricated metal products",
        "start": "1948-01-01",
        "end": "1987-01-01",
        "frequency": "Annual",
        "units": "Millions of Dollars",
        "popularity": 0
    },
    "J4020C0A144NBEA": {
        "title": "Compensation of employees: Domestic private industries: Manufacturing: Durable goods: Machinery, except electrical",
        "start": "1948-01-01",
        "end": "1987-01-01",
        "frequency": "Annual",
        "units": "Millions of Dollars",
        "popularity": 1
    },
    "J4021C0A144NBEA": {
        "title": "Compensation of employees: Domestic private industries: Manufacturing: Durable goods: Electric and electronic equipment",
        "start": "1948-01-01",
        "end": "1987-01-01",
        "frequency": "Annual",
        "units": "Millions of Dollars",
        "popularity": 0
    },
    "J4022C0A144NBEA": {
        "title": "Compensation of employees: Domestic private industries: Manufacturing: Durable goods: Motor vehicles and equipment",
        "start": "1948-01-01",
        "end": "1987-01-01",
        "frequency": "Annual",
        "units": "Millions of Dollars",
        "popularity": 1
    },
    "J4023C0A144NBEA": {
        "title": "Compensation of employees: Domestic private industries: Manufacturing: Durable goods: Other transportation equipment",
        "start": "1948-01-01",
        "end": "1987-01-01",
        "frequency": "Annual",
        "units": "Millions of Dollars",
        "popularity": 1
    },
    "J4024C0A144NBEA": {
        "title": "Compensation of employees: Domestic private industries: Manufacturing: Durable goods: Instruments and related products",
        "start": "1948-01-01",
        "end": "1987-01-01",
        "frequency": "Annual",
        "units": "Millions of Dollars",
        "popularity": 0
    },
    "J4025C0A144NBEA": {
        "title": "Compensation of employees: Domestic private industries: Manufacturing: Durable goods: Miscellaneous manufacturing industries",
        "start": "1948-01-01",
        "end": "1987-01-01",
        "frequency": "Annual",
        "units": "Millions of Dollars",
        "popularity": 0
    },
    "J4026C0A144NBEA": {
        "title": "Compensation of employees: Domestic private industries: Manufacturing: Nondurable goods (DISCONTINUED)",
        "start": "1948-01-01",
        "end": "1969-01-01",
        "frequency": "Annual",
        "units": "Millions of Dollars",
        "popularity": 1
    },
    "J4027C0A144NBEA": {
        "title": "Compensation of employees: Domestic private industries: Manufacturing: Nondurable goods: Food and kindred products",
        "start": "1948-01-01",
        "end": "1987-01-01",
        "frequency": "Annual",
        "units": "Millions of Dollars",
        "popularity": 1
    },
    "J4029C0A144NBEA": {
        "title": "Compensation of employees: Domestic private industries: Manufacturing: Nondurable goods: Textile mill products",
        "start": "1948-01-01",
        "end": "1987-01-01",
        "frequency": "Annual",
        "units": "Millions of Dollars",
        "popularity": 0
    },
    "J4030C0A144NBEA": {
        "title": "Compensation of employees: Domestic private industries: Manufacturing: Nondurable goods: Apparel and other textile products",
        "start": "1948-01-01",
        "end": "1987-01-01",
        "frequency": "Annual",
        "units": "Millions of Dollars",
        "popularity": 1
    },
    "J4031C0A144NBEA": {
        "title": "Compensation of employees: Domestic private industries: Manufacturing: Nondurable goods: Paper and allied products",
        "start": "1987-01-01",
        "end": "2000-01-01",
        "frequency": "Annual",
        "units": "Millions of Dollars",
        "popularity": 1
    },
    "J4032C0A144NBEA": {
        "title": "Compensation of employees: Domestic private industries: Manufacturing: Nondurable goods: Printing and publishing",
        "start": "1948-01-01",
        "end": "1987-01-01",
        "frequency": "Annual",
        "units": "Millions of Dollars",
        "popularity": 1
    },
    "J4033C0A144NBEA": {
        "title": "Compensation of employees: Domestic private industries: Manufacturing: Nondurable goods: Chemicals and allied products",
        "start": "1948-01-01",
        "end": "1987-01-01",
        "frequency": "Annual",
        "units": "Millions of Dollars",
        "popularity": 0
    },
    "J4034C0A144NBEA": {
        "title": "Compensation of employees: Domestic private industries: Manufacturing: Nondurable goods: Petroleum and coal products",
        "start": "1948-01-01",
        "end": "1987-01-01",
        "frequency": "Annual",
        "units": "Millions of Dollars",
        "popularity": 0
    },
    "J4035C0A144NBEA": {
        "title": "Compensation of employees: Domestic private industries: Manufacturing: Nondurable goods: Rubber and miscellaneous plastics products",
        "start": "1948-01-01",
        "end": "1987-01-01",
        "frequency": "Annual",
        "units": "Millions of Dollars",
        "popularity": 0
    },
    "J4036C0A144NBEA": {
        "title": "Compensation of employees: Domestic private industries: Manufacturing: Nondurable goods: Leather and leather products",
        "start": "1948-01-01",
        "end": "1987-01-01",
        "frequency": "Annual",
        "units": "Millions of Dollars",
        "popularity": 0
    },
    "J4038C0A144NBEA": {
        "title": "Compensation of employees: Domestic private industries: Transportation",
        "start": "1987-01-01",
        "end": "2000-01-01",
        "frequency": "Annual",
        "units": "Millions of Dollars",
        "popularity": 0
    },
    "J4040C0A144NBEA": {
        "title": "Compensation of employees: Domestic private industries: Transportation: Local and interurban passenger transit",
        "start": "1948-01-01",
        "end": "1987-01-01",
        "frequency": "Annual",
        "units": "Millions of Dollars",
        "popularity": 0
    },
    "J4042C0A144NBEA": {
        "title": "Compensation of employees: Domestic private industries: Water transportation",
        "start": "1948-01-01",
        "end": "1987-01-01",
        "frequency": "Annual",
        "units": "Millions of Dollars",
        "popularity": 0
    },
    "J4043C0A144NBEA": {
        "title": "Compensation of employees: Domestic private industries: Transportation by air",
        "start": "1948-01-01",
        "end": "1987-01-01",
        "frequency": "Annual",
        "units": "Millions of Dollars",
        "popularity": 0
    },
    "J4045C0A144NBEA": {
        "title": "Compensation of employees: Domestic private industries: Transportation services",
        "start": "1948-01-01",
        "end": "1987-01-01",
        "frequency": "Annual",
        "units": "Millions of Dollars",
        "popularity": 0
    },
    "J4046C0A144NBEA": {
        "title": "Compensation of employees: Domestic private industries: Communication",
        "start": "1987-01-01",
        "end": "2000-01-01",
        "frequency": "Annual",
        "units": "Millions of Dollars",
        "popularity": 1
    },
    "J4047C0A144NBEA": {
        "title": "Compensation of employees: Domestic private industries: Communication: Telephone and telegraph",
        "start": "1987-01-01",
        "end": "2000-01-01",
        "frequency": "Annual",
        "units": "Millions of Dollars",
        "popularity": 0
    },
    "J4048C0A144NBEA": {
        "title": "Compensation of employees: Domestic private industries: Communication: Radio and television",
        "start": "1987-01-01",
        "end": "2000-01-01",
        "frequency": "Annual",
        "units": "Millions of Dollars",
        "popularity": 0
    },
    "J4049C0A144NBEA": {
        "title": "Compensation of employees: Domestic private industries: Transportation and public utilities: Electric, gas, and sanitary services",
        "start": "1987-01-01",
        "end": "2000-01-01",
        "frequency": "Annual",
        "units": "Millions of Dollars",
        "popularity": 1
    },
    "J4050C0A144NBEA": {
        "title": "Compensation of employees: Domestic private industries: Wholesale trade (DISCONTINUED)",
        "start": "1948-01-01",
        "end": "1969-01-01",
        "frequency": "Annual",
        "units": "Millions of Dollars",
        "popularity": 0
    },
    "J4051C0A144NBEA": {
        "title": "Compensation of employees: Domestic private industries: Retail trade (DISCONTINUED)",
        "start": "1948-01-01",
        "end": "1969-01-01",
        "frequency": "Annual",
        "units": "Millions of Dollars",
        "popularity": 1
    },
    "J4052C0A144NBEA": {
        "title": "Compensation of employees: Domestic private industries: Finance, insurance, and real estate (DISCONTINUED)",
        "start": "1948-01-01",
        "end": "1969-01-01",
        "frequency": "Annual",
        "units": "Millions of Dollars",
        "popularity": 1
    },
    "J4053C0A144NBEA": {
        "title": "Compensation of employees: Domestic private industries: Banking",
        "start": "1948-01-01",
        "end": "1987-01-01",
        "frequency": "Annual",
        "units": "Millions of Dollars",
        "popularity": 1
    },
    "J4054C0A144NBEA": {
        "title": "Compensation of employees: Domestic private industries: Credit agencies other than banks",
        "start": "1948-01-01",
        "end": "1987-01-01",
        "frequency": "Annual",
        "units": "Millions of Dollars",
        "popularity": 1
    },
    "J4055C0A144NBEA": {
        "title": "Compensation of employees: Domestic private industries: Security and commodity brokers",
        "start": "1948-01-01",
        "end": "1987-01-01",
        "frequency": "Annual",
        "units": "Millions of Dollars",
        "popularity": 1
    },
    "J4057C0A144NBEA": {
        "title": "Compensation of employees: Domestic private industries: Insurance agents, brokers, and service",
        "start": "1948-01-01",
        "end": "1987-01-01",
        "frequency": "Annual",
        "units": "Millions of Dollars",
        "popularity": 1
    },
    "J4058C0A144NBEA": {
        "title": "Compensation of employees: Domestic private industries: Real estate",
        "start": "1948-01-01",
        "end": "1987-01-01",
        "frequency": "Annual",
        "units": "Millions of Dollars",
        "popularity": 1
    },
    "J4060C0A144NBEA": {
        "title": "Compensation of employees: Domestic private industries: Services (DISCONTINUED)",
        "start": "1948-01-01",
        "end": "1969-01-01",
        "frequency": "Annual",
        "units": "Millions of Dollars",
        "popularity": 1
    },
    "J4062C0A144NBEA": {
        "title": "Compensation of employees: Domestic private industries: Personal services",
        "start": "1987-01-01",
        "end": "2000-01-01",
        "frequency": "Annual",
        "units": "Millions of Dollars",
        "popularity": 0
    },
    "J4063C0A144NBEA": {
        "title": "Compensation of employees: Domestic private industries: Business services",
        "start": "1948-01-01",
        "end": "1987-01-01",
        "frequency": "Annual",
        "units": "Millions of Dollars",
        "popularity": 1
    },
    "J4066C0A144NBEA": {
        "title": "Compensation of employees: Domestic private industries: Services: Motion pictures",
        "start": "1987-01-01",
        "end": "2000-01-01",
        "frequency": "Annual",
        "units": "Millions of Dollars",
        "popularity": 1
    },
    "J4067C0A144NBEA": {
        "title": "Compensation of employees: Domestic private industries: Amusement and recreation services",
        "start": "1987-01-01",
        "end": "2000-01-01",
        "frequency": "Annual",
        "units": "Millions of Dollars",
        "popularity": 0
    },
    "J4068C0A144NBEA": {
        "title": "Compensation of employees: Domestic private industries: Health services",
        "start": "1948-01-01",
        "end": "1987-01-01",
        "frequency": "Annual",
        "units": "Millions of Dollars",
        "popularity": 0
    },
    "J4069C0A144NBEA": {
        "title": "Compensation of employees: Domestic private industries: Legal services",
        "start": "1948-01-01",
        "end": "1987-01-01",
        "frequency": "Annual",
        "units": "Millions of Dollars",
        "popularity": 1
    },
    "J4070C0A144NBEA": {
        "title": "Compensation of employees: Domestic private industries: Educational services",
        "start": "1948-01-01",
        "end": "1987-01-01",
        "frequency": "Annual",
        "units": "Millions of Dollars",
        "popularity": 1
    },
    "J4071C0A144NBEA": {
        "title": "Compensation of employees: Domestic private industries: Social services and membership organizations",
        "start": "1948-01-01",
        "end": "1987-01-01",
        "frequency": "Annual",
        "units": "Millions of Dollars",
        "popularity": 1
    },
    "J4074C0A144NBEA": {
        "title": "Compensation of employees: Domestic private industries: Miscellaneous professional services",
        "start": "1948-01-01",
        "end": "1987-01-01",
        "frequency": "Annual",
        "units": "Millions of Dollars",
        "popularity": 0
    },
    "N4004C0A144NBEA": {
        "title": "Compensation of employees: Domestic private industries: Agriculture, forestry, fishing, and hunting",
        "start": "1998-01-01",
        "end": "2021-01-01",
        "frequency": "Annual",
        "units": "Millions of Dollars",
        "popularity": 1
    },
    "N4005C0A144NBEA": {
        "title": "Compensation of employees: Domestic private industries: Farms",
        "start": "1998-01-01",
        "end": "2021-01-01",
        "frequency": "Annual",
        "units": "Millions of Dollars",
        "popularity": 1
    },
    "N4006C0A144NBEA": {
        "title": "Compensation of employees: Domestic private industries: Forestry, fishing, and related activities",
        "start": "1998-01-01",
        "end": "2021-01-01",
        "frequency": "Annual",
        "units": "Millions of Dollars",
        "popularity": 1
    },
    "N4007C0A144NBEA": {
        "title": "Compensation of employees: Domestic private industries: Mining",
        "start": "1998-01-01",
        "end": "2021-01-01",
        "frequency": "Annual",
        "units": "Millions of Dollars",
        "popularity": 1
    },
    "N4008C0A144NBEA": {
        "title": "Compensation of employees: Domestic private industries: Mining: Oil and gas extraction",
        "start": "1998-01-01",
        "end": "2021-01-01",
        "frequency": "Annual",
        "units": "Millions of Dollars",
        "popularity": 1
    },
    "N4009C0A144NBEA": {
        "title": "Compensation of employees: Domestic private industries: Mining, except oil and gas",
        "start": "1998-01-01",
        "end": "2021-01-01",
        "frequency": "Annual",
        "units": "Millions of Dollars",
        "popularity": 1
    },
    "N4010C0A144NBEA": {
        "title": "Compensation of employees: Domestic private industries: Support activities for mining",
        "start": "1998-01-01",
        "end": "2021-01-01",
        "frequency": "Annual",
        "units": "Millions of Dollars",
        "popularity": 1
    },
    "N4011C0A144NBEA": {
        "title": "Compensation of employees: Domestic private industries: Utilities",
        "start": "1998-01-01",
        "end": "2021-01-01",
        "frequency": "Annual",
        "units": "Millions of Dollars",
        "popularity": 1
    },
    "N4012C0A144NBEA": {
        "title": "Compensation of employees: Domestic private industries: Construction",
        "start": "1998-01-01",
        "end": "2021-01-01",
        "frequency": "Annual",
        "units": "Millions of Dollars",
        "popularity": 1
    },
    "N4013C0A144NBEA": {
        "title": "Compensation of employees: Domestic private industries: Manufacturing",
        "start": "1998-01-01",
        "end": "2021-01-01",
        "frequency": "Annual",
        "units": "Millions of Dollars",
        "popularity": 1
    },
    "N4014C0A144NBEA": {
        "title": "Compensation of employees: Domestic private industries: Manufacturing: Durable goods",
        "start": "1998-01-01",
        "end": "2021-01-01",
        "frequency": "Annual",
        "units": "Millions of Dollars",
        "popularity": 1
    },
    "N4015C0A144NBEA": {
        "title": "Compensation of employees: Domestic private industries: Manufacturing: Durable goods: Wood products",
        "start": "1998-01-01",
        "end": "2021-01-01",
        "frequency": "Annual",
        "units": "Millions of Dollars",
        "popularity": 1
    },
    "N4016C0A144NBEA": {
        "title": "Compensation of employees: Domestic private industries: Manufacturing: Durable goods: Nonmetallic mineral products",
        "start": "1998-01-01",
        "end": "2021-01-01",
        "frequency": "Annual",
        "units": "Millions of Dollars",
        "popularity": 1
    },
    "N4017C0A144NBEA": {
        "title": "Compensation of employees: Domestic private industries: Manufacturing: Durable goods: Primary metals",
        "start": "1998-01-01",
        "end": "2021-01-01",
        "frequency": "Annual",
        "units": "Millions of Dollars",
        "popularity": 1
    },
    "N4018C0A144NBEA": {
        "title": "Compensation of employees: Domestic private industries: Manufacturing: Durable goods: Fabricated metal products",
        "start": "1998-01-01",
        "end": "2021-01-01",
        "frequency": "Annual",
        "units": "Millions of Dollars",
        "popularity": 1
    },
    "N4019C0A144NBEA": {
        "title": "Compensation of employees: Domestic private industries: Manufacturing: Durable goods: Machinery",
        "start": "1998-01-01",
        "end": "2021-01-01",
        "frequency": "Annual",
        "units": "Millions of Dollars",
        "popularity": 1
    },
    "N4020C0A144NBEA": {
        "title": "Compensation of employees: Domestic private industries: Manufacturing: Durable goods: Computer and electronic products",
        "start": "1998-01-01",
        "end": "2021-01-01",
        "frequency": "Annual",
        "units": "Millions of Dollars",
        "popularity": 1
    },
    "N4021C0A144NBEA": {
        "title": "Compensation of employees: Domestic private industries: Manufacturing: Durable goods: Electrical equipment, appliances, and components",
        "start": "1998-01-01",
        "end": "2021-01-01",
        "frequency": "Annual",
        "units": "Millions of Dollars",
        "popularity": 1
    },
    "N4022C0A144NBEA": {
        "title": "Compensation of employees: Domestic private industries: Manufacturing: Durable goods: Motor vehicles, bodies and trailers, and parts",
        "start": "1998-01-01",
        "end": "2021-01-01",
        "frequency": "Annual",
        "units": "Millions of Dollars",
        "popularity": 1
    },
    "N4023C0A144NBEA": {
        "title": "Compensation of employees: Domestic private industries: Manufacturing: Durable goods: Other transportation equipment",
        "start": "1998-01-01",
        "end": "2021-01-01",
        "frequency": "Annual",
        "units": "Millions of Dollars",
        "popularity": 1
    },
    "N4024C0A144NBEA": {
        "title": "Compensation of employees: Domestic private industries: Manufacturing: Durable goods: Furniture and related products",
        "start": "1998-01-01",
        "end": "2021-01-01",
        "frequency": "Annual",
        "units": "Millions of Dollars",
        "popularity": 1
    },
    "N4025C0A144NBEA": {
        "title": "Compensation of employees: Domestic private industries: Manufacturing: Durable goods: Miscellaneous manufacturing",
        "start": "1998-01-01",
        "end": "2021-01-01",
        "frequency": "Annual",
        "units": "Millions of Dollars",
        "popularity": 1
    },
    "N4026C0A144NBEA": {
        "title": "Compensation of employees: Domestic private industries: Manufacturing: Nondurable goods",
        "start": "1998-01-01",
        "end": "2021-01-01",
        "frequency": "Annual",
        "units": "Millions of Dollars",
        "popularity": 1
    },
    "N4027C0A144NBEA": {
        "title": "Compensation of employees: Domestic private industries: Manufacturing: Nondurable goods: Food and beverage and tobacco products",
        "start": "1998-01-01",
        "end": "2021-01-01",
        "frequency": "Annual",
        "units": "Millions of Dollars",
        "popularity": 1
    },
    "N4029C0A144NBEA": {
        "title": "Compensation of employees: Domestic private industries: Manufacturing: Nondurable goods: Textile mills and textile product mills",
        "start": "1998-01-01",
        "end": "2021-01-01",
        "frequency": "Annual",
        "units": "Millions of Dollars",
        "popularity": 1
    },
    "N4030C0A144NBEA": {
        "title": "Compensation of employees: Domestic private industries: Manufacturing: Nondurable goods: Apparel and leather and allied products",
        "start": "1998-01-01",
        "end": "2021-01-01",
        "frequency": "Annual",
        "units": "Millions of Dollars",
        "popularity": 1
    },
    "N4032C0A144NBEA": {
        "title": "Compensation of employees: Domestic private industries: Manufacturing: Nondurable goods: Paper products",
        "start": "1998-01-01",
        "end": "2021-01-01",
        "frequency": "Annual",
        "units": "Millions of Dollars",
        "popularity": 1
    },
    "N4033C0A144NBEA": {
        "title": "Compensation of employees: Domestic private industries: Manufacturing: Nondurable goods: Printing and related support activities",
        "start": "1998-01-01",
        "end": "2021-01-01",
        "frequency": "Annual",
        "units": "Millions of Dollars",
        "popularity": 1
    },
    "N4034C0A144NBEA": {
        "title": "Compensation of employees: Domestic private industries: Manufacturing: Nondurable goods: Petroleum and coal products",
        "start": "1998-01-01",
        "end": "2021-01-01",
        "frequency": "Annual",
        "units": "Millions of Dollars",
        "popularity": 0
    },
    "N4035C0A144NBEA": {
        "title": "Compensation of employees: Domestic private industries: Manufacturing: Nondurable goods: Chemical products",
        "start": "1998-01-01",
        "end": "2021-01-01",
        "frequency": "Annual",
        "units": "Millions of Dollars",
        "popularity": 1
    },
    "N4036C0A144NBEA": {
        "title": "Compensation of employees: Domestic private industries: Manufacturing: Nondurable goods: Plastics and rubber products",
        "start": "1998-01-01",
        "end": "2021-01-01",
        "frequency": "Annual",
        "units": "Millions of Dollars",
        "popularity": 1
    },
    "N4037C0A144NBEA": {
        "title": "Compensation of employees: Domestic private industries: Wholesale trade",
        "start": "1998-01-01",
        "end": "2021-01-01",
        "frequency": "Annual",
        "units": "Millions of Dollars",
        "popularity": 1
    },
    "N4038C0A144NBEA": {
        "title": "Compensation of employees: Domestic private industries: Wholesale trade: Durable goods",
        "start": "1998-01-01",
        "end": "2021-01-01",
        "frequency": "Annual",
        "units": "Millions of Dollars",
        "popularity": 1
    },
    "N4039C0A144NBEA": {
        "title": "Compensation of employees: Domestic private industries: Wholesale trade: Nondurable goods",
        "start": "1998-01-01",
        "end": "2021-01-01",
        "frequency": "Annual",
        "units": "Millions of Dollars",
        "popularity": 1
    },
    "N4040C0A144NBEA": {
        "title": "Compensation of employees: Domestic private industries: Retail trade",
        "start": "1998-01-01",
        "end": "2021-01-01",
        "frequency": "Annual",
        "units": "Millions of Dollars",
        "popularity": 1
    },
    "N4041C0A144NBEA": {
        "title": "Compensation of employees: Domestic private industries: Retail trade: Motor vehicle and parts dealers",
        "start": "1998-01-01",
        "end": "2021-01-01",
        "frequency": "Annual",
        "units": "Millions of Dollars",
        "popularity": 1
    },
    "N4042C0A144NBEA": {
        "title": "Compensation of employees: Domestic private industries: Retail trade: Food and beverage stores",
        "start": "1998-01-01",
        "end": "2021-01-01",
        "frequency": "Annual",
        "units": "Millions of Dollars",
        "popularity": 1
    },
    "N4043C0A144NBEA": {
        "title": "Compensation of employees: Domestic private industries: Retail trade: General merchandise stores",
        "start": "1998-01-01",
        "end": "2021-01-01",
        "frequency": "Annual",
        "units": "Millions of Dollars",
        "popularity": 1
    },
    "N4044C0A144NBEA": {
        "title": "Compensation of employees: Domestic private industries: Retail trade: Other retail",
        "start": "1998-01-01",
        "end": "2021-01-01",
        "frequency": "Annual",
        "units": "Millions of Dollars",
        "popularity": 1
    },
    "N4045C0A144NBEA": {
        "title": "Compensation of employees: Domestic private industries: Transportation and warehousing",
        "start": "1998-01-01",
        "end": "2021-01-01",
        "frequency": "Annual",
        "units": "Millions of Dollars",
        "popularity": 1
    },
    "N4046C0A144NBEA": {
        "title": "Compensation of employees: Domestic private industries: Air transportation",
        "start": "1998-01-01",
        "end": "2021-01-01",
        "frequency": "Annual",
        "units": "Millions of Dollars",
        "popularity": 1
    },
    "N4047C0A144NBEA": {
        "title": "Compensation of employees: Domestic private industries: Rail transportation",
        "start": "1998-01-01",
        "end": "2021-01-01",
        "frequency": "Annual",
        "units": "Millions of Dollars",
        "popularity": 1
    },
    "N4048C0A144NBEA": {
        "title": "Compensation of employees: Domestic private industries: Water transportation",
        "start": "1998-01-01",
        "end": "2021-01-01",
        "frequency": "Annual",
        "units": "Millions of Dollars",
        "popularity": 1
    },
    "N4049C0A144NBEA": {
        "title": "Compensation of employees: Domestic private industries: Truck transportation",
        "start": "1998-01-01",
        "end": "2021-01-01",
        "frequency": "Annual",
        "units": "Millions of Dollars",
        "popularity": 1
    },
    "N4050C0A144NBEA": {
        "title": "Compensation of employees: Domestic private industries: Transit and ground passenger transportation",
        "start": "1998-01-01",
        "end": "2021-01-01",
        "frequency": "Annual",
        "units": "Millions of Dollars",
        "popularity": 1
    },
    "N4051C0A144NBEA": {
        "title": "Compensation of employees: Domestic private industries: Pipeline transportation",
        "start": "1998-01-01",
        "end": "2021-01-01",
        "frequency": "Annual",
        "units": "Millions of Dollars",
        "popularity": 1
    },
    "N4052C0A144NBEA": {
        "title": "Compensation of employees: Domestic private industries: Other transportation and support activities",
        "start": "1998-01-01",
        "end": "2021-01-01",
        "frequency": "Annual",
        "units": "Millions of Dollars",
        "popularity": 1
    },
    "N4053C0A144NBEA": {
        "title": "Compensation of employees: Domestic private industries: Warehousing and storage",
        "start": "1998-01-01",
        "end": "2021-01-01",
        "frequency": "Annual",
        "units": "Millions of Dollars",
        "popularity": 1
    },
    "N4054C0A144NBEA": {
        "title": "Compensation of employees: Domestic private industries: Information",
        "start": "1998-01-01",
        "end": "2021-01-01",
        "frequency": "Annual",
        "units": "Millions of Dollars",
        "popularity": 1
    },
    "N4055C0A144NBEA": {
        "title": "Compensation of employees: Domestic private industries: Information: Publishing industries (includes software)",
        "start": "1998-01-01",
        "end": "2021-01-01",
        "frequency": "Annual",
        "units": "Millions of Dollars",
        "popularity": 1
    },
    "N4056C0A144NBEA": {
        "title": "Compensation of employees: Domestic private industries: Information: Motion picture and sound recording industries",
        "start": "1998-01-01",
        "end": "2021-01-01",
        "frequency": "Annual",
        "units": "Millions of Dollars",
        "popularity": 1
    },
    "N4057C0A144NBEA": {
        "title": "Compensation of employees: Domestic private industries: Information: Broadcasting and telecommunications",
        "start": "1998-01-01",
        "end": "2021-01-01",
        "frequency": "Annual",
        "units": "Millions of Dollars",
        "popularity": 1
    },
    "N4058C0A144NBEA": {
        "title": "Compensation of employees: Domestic private industries: Information: Information and data processing services",
        "start": "1998-01-01",
        "end": "2021-01-01",
        "frequency": "Annual",
        "units": "Millions of Dollars",
        "popularity": 1
    },
    "N4059C0A144NBEA": {
        "title": "Compensation of employees: Domestic private industries: Finance and insurance",
        "start": "1998-01-01",
        "end": "2021-01-01",
        "frequency": "Annual",
        "units": "Millions of Dollars",
        "popularity": 1
    },
    "N4060C0A144NBEA": {
        "title": "Compensation of employees: Domestic private industries: Federal Reserve banks, credit intermediation, and related activities",
        "start": "1998-01-01",
        "end": "2021-01-01",
        "frequency": "Annual",
        "units": "Millions of Dollars",
        "popularity": 1
    },
    "N4061C0A144NBEA": {
        "title": "Compensation of employees: Domestic private industries: Securities, commodity contracts, and investments",
        "start": "1998-01-01",
        "end": "2021-01-01",
        "frequency": "Annual",
        "units": "Millions of Dollars",
        "popularity": 1
    },
    "N4062C0A144NBEA": {
        "title": "Compensation of employees: Domestic private industries: Insurance carriers and related activities",
        "start": "1998-01-01",
        "end": "2021-01-01",
        "frequency": "Annual",
        "units": "Millions of Dollars",
        "popularity": 1
    },
    "N4063C0A144NBEA": {
        "title": "Compensation of employees: Domestic private industries: Funds, trusts, and other financial vehicles",
        "start": "1998-01-01",
        "end": "2021-01-01",
        "frequency": "Annual",
        "units": "Millions of Dollars",
        "popularity": 1
    },
    "N4064C0A144NBEA": {
        "title": "Compensation of employees: Domestic private industries: Real estate and rental and leasing",
        "start": "1998-01-01",
        "end": "2021-01-01",
        "frequency": "Annual",
        "units": "Millions of Dollars",
        "popularity": 1
    },
    "N4065C0A144NBEA": {
        "title": "Compensation of employees: Domestic private industries: Real estate",
        "start": "1998-01-01",
        "end": "2021-01-01",
        "frequency": "Annual",
        "units": "Millions of Dollars",
        "popularity": 0
    },
    "N4066C0A144NBEA": {
        "title": "Compensation of employees: Domestic private industries: Rental and leasing services and lessors of intangible assets",
        "start": "1998-01-01",
        "end": "2021-01-01",
        "frequency": "Annual",
        "units": "Millions of Dollars",
        "popularity": 1
    },
    "N4067C0A144NBEA": {
        "title": "Compensation of employees: Domestic private industries: Professional, scientific, and technical services",
        "start": "1998-01-01",
        "end": "2021-01-01",
        "frequency": "Annual",
        "units": "Millions of Dollars",
        "popularity": 1
    },
    "N4068C0A144NBEA": {
        "title": "Compensation of employees: Domestic private industries: Legal services",
        "start": "1998-01-01",
        "end": "2021-01-01",
        "frequency": "Annual",
        "units": "Millions of Dollars",
        "popularity": 1
    },
    "N4069C0A144NBEA": {
        "title": "Compensation of employees: Domestic private industries: Computer systems design and related services",
        "start": "1998-01-01",
        "end": "2021-01-01",
        "frequency": "Annual",
        "units": "Millions of Dollars",
        "popularity": 1
    },
    "N4070C0A144NBEA": {
        "title": "Compensation of employees: Domestic private industries: Miscellaneous professional, scientific, and technical services",
        "start": "1998-01-01",
        "end": "2021-01-01",
        "frequency": "Annual",
        "units": "Millions of Dollars",
        "popularity": 1
    },
    "N4071C0A144NBEA": {
        "title": "Compensation of employees: Domestic private industries: Management of companies and enterprises",
        "start": "1998-01-01",
        "end": "2021-01-01",
        "frequency": "Annual",
        "units": "Millions of Dollars",
        "popularity": 1
    },
    "N4072C0A144NBEA": {
        "title": "Compensation of employees: Domestic private industries: Administrative and waste management services",
        "start": "1998-01-01",
        "end": "2021-01-01",
        "frequency": "Annual",
        "units": "Millions of Dollars",
        "popularity": 1
    },
    "N4073C0A144NBEA": {
        "title": "Compensation of employees: Domestic private industries: Administrative and support services",
        "start": "1998-01-01",
        "end": "2021-01-01",
        "frequency": "Annual",
        "units": "Millions of Dollars",
        "popularity": 1
    },
    "N4074C0A144NBEA": {
        "title": "Compensation of employees: Domestic private industries: Waste management and remediation services",
        "start": "1998-01-01",
        "end": "2021-01-01",
        "frequency": "Annual",
        "units": "Millions of Dollars",
        "popularity": 1
    },
    "N4075C0A144NBEA": {
        "title": "Compensation of employees: Domestic private industries: Educational services",
        "start": "1998-01-01",
        "end": "2021-01-01",
        "frequency": "Annual",
        "units": "Millions of Dollars",
        "popularity": 1
    },
    "N4076C0A144NBEA": {
        "title": "Compensation of employees: Domestic private industries: Health care and social assistance",
        "start": "1998-01-01",
        "end": "2021-01-01",
        "frequency": "Annual",
        "units": "Millions of Dollars",
        "popularity": 1
    },
    "N4077C0A144NBEA": {
        "title": "Compensation of employees: Domestic private industries: Ambulatory health care services",
        "start": "1998-01-01",
        "end": "2021-01-01",
        "frequency": "Annual",
        "units": "Millions of Dollars",
        "popularity": 1
    },
    "N4078C0A144NBEA": {
        "title": "Compensation of employees: Domestic private industries: Hospitals",
        "start": "1998-01-01",
        "end": "2021-01-01",
        "frequency": "Annual",
        "units": "Millions of Dollars",
        "popularity": 1
    },
    "N4079C0A144NBEA": {
        "title": "Compensation of employees: Domestic private industries: Nursing and residential care facilities",
        "start": "1998-01-01",
        "end": "2021-01-01",
        "frequency": "Annual",
        "units": "Millions of Dollars",
        "popularity": 1
    },
    "N4080C0A144NBEA": {
        "title": "Compensation of employees: Domestic private industries: Social assistance",
        "start": "1998-01-01",
        "end": "2021-01-01",
        "frequency": "Annual",
        "units": "Millions of Dollars",
        "popularity": 1
    },
    "N4081C0A144NBEA": {
        "title": "Compensation of employees: Domestic private industries: Arts, entertainment, and recreation",
        "start": "1998-01-01",
        "end": "2021-01-01",
        "frequency": "Annual",
        "units": "Millions of Dollars",
        "popularity": 1
    },
    "N4082C0A144NBEA": {
        "title": "Compensation of employees: Domestic private industries: Performing arts, spectator sports, museums, and related activities",
        "start": "1998-01-01",
        "end": "2021-01-01",
        "frequency": "Annual",
        "units": "Millions of Dollars",
        "popularity": 1
    },
    "N4083C0A144NBEA": {
        "title": "Compensation of employees: Domestic private industries: Amusements, gambling, and recreation industries",
        "start": "1998-01-01",
        "end": "2021-01-01",
        "frequency": "Annual",
        "units": "Millions of Dollars",
        "popularity": 1
    },
    "N4084C0A144NBEA": {
        "title": "Compensation of employees: Domestic private industries: Accommodation and food services",
        "start": "1998-01-01",
        "end": "2021-01-01",
        "frequency": "Annual",
        "units": "Millions of Dollars",
        "popularity": 1
    },
    "N4085C0A144NBEA": {
        "title": "Compensation of employees: Domestic private industries: Accommodation",
        "start": "1998-01-01",
        "end": "2021-01-01",
        "frequency": "Annual",
        "units": "Millions of Dollars",
        "popularity": 1
    },
    "N4086C0A144NBEA": {
        "title": "Compensation of employees: Domestic private industries: Food services and drinking places",
        "start": "1998-01-01",
        "end": "2021-01-01",
        "frequency": "Annual",
        "units": "Millions of Dollars",
        "popularity": 1
    },
    "N4087C0A144NBEA": {
        "title": "Compensation of employees: Domestic private industries: Other services, except government",
        "start": "1998-01-01",
        "end": "2021-01-01",
        "frequency": "Annual",
        "units": "Millions of Dollars",
        "popularity": 1
    },
    "NA000271Q": {
        "title": "Compensation of employees: Supplements to wages and salaries",
        "start": "2002-01-01",
        "end": "2022-07-01",
        "frequency": "Quarterly",
        "units": "Millions of Dollars",
        "popularity": 1
    },
    "W151RC0A144NBEA": {
        "title": "National income: Households: Compensation of employees (DISCONTINUED)",
        "start": "1929-01-01",
        "end": "2000-01-01",
        "frequency": "Annual",
        "units": "Millions of Dollars",
        "popularity": 1
    },
    "W151RC1A027NBEA": {
        "title": "National income: Households: Compensation of employees",
        "start": "1929-01-01",
        "end": "2021-01-01",
        "frequency": "Annual",
        "units": "Billions of Dollars",
        "popularity": 3
    },
    "W152RC1A027NBEA": {
        "title": "National income: Households and institutions: Nonprofit institutions serving households: Compensation of employees",
        "start": "1929-01-01",
        "end": "2021-01-01",
        "frequency": "Annual",
        "units": "Billions of Dollars",
        "popularity": 1
    },
    "W209RC1A027NBEA": {
        "title": "Compensation of employees (DISCONTINUED)",
        "start": "1929-01-01",
        "end": "2014-01-01",
        "frequency": "Annual",
        "units": "Billions of Dollars",
        "popularity": 1
    },
    "W209RC1Q027SBEA": {
        "title": "Compensation of employees (DISCONTINUED)",
        "start": "1947-01-01",
        "end": "2015-04-01",
        "frequency": "Quarterly",
        "units": "Billions of Dollars",
        "popularity": 1
    },
    "W4080C0A144NBEA": {
        "title": "Compensation of employees: Federal general government: Military",
        "start": "1948-01-01",
        "end": "2021-01-01",
        "frequency": "Annual",
        "units": "Millions of Dollars",
        "popularity": 1
    },
    "W462RC1A027NBEA": {
        "title": "National income: Domestic business: Noncorporate business: Compensation of employees",
        "start": "1948-01-01",
        "end": "2021-01-01",
        "frequency": "Annual",
        "units": "Billions of Dollars",
        "popularity": 1
    },
    "W464RC1A027NBEA": {
        "title": "National income: Domestic business: Noncorporate business: Compensation of employees: Supplements to wages and salaries",
        "start": "1948-01-01",
        "end": "2021-01-01",
        "frequency": "Annual",
        "units": "Billions of Dollars",
        "popularity": 1
    },
    "W482RC1A027NBEA": {
        "title": "National income: Households and institutions: Nonprofit institutions serving households: Compensation of employees: Supplements to wages and salaries",
        "start": "1948-01-01",
        "end": "2021-01-01",
        "frequency": "Annual",
        "units": "Billions of Dollars",
        "popularity": 1
    },
    "W506RC0A144NBEA": {
        "title": "Compensation of employees: Households and institutions",
        "start": "1929-01-01",
        "end": "2000-01-01",
        "frequency": "Annual",
        "units": "Millions of Dollars",
        "popularity": 1
    },
    "Y239RC1A027NBEA": {
        "title": "Supplements to Wages and Salaries: Pension and other employee benefit plans: State and local employee retirement",
        "start": "1929-01-01",
        "end": "2021-01-01",
        "frequency": "Annual",
        "units": "Billions of Dollars",
        "popularity": 1
    },
    "Y390RC1A027NBEA": {
        "title": "Supplements to Wages and Salaries: Health insurance: Publicly administered government employee insurance funds",
        "start": "2002-01-01",
        "end": "2021-01-01",
        "frequency": "Annual",
        "units": "Billions of Dollars",
        "popularity": 1
    }
}