{
    "2020RATIO042111": {
        "title": "Income Inequality in Somerset County, PA",
        "start": "2010-01-01",
        "end": "2021-01-01",
        "frequency": "Annual",
        "units": "Ratio",
        "popularity": 0
    },
    "ACTLISCOU42111": {
        "title": "Housing Inventory: Active Listing Count in Somerset County, PA",
        "start": "2016-07-01",
        "end": "2022-11-01",
        "frequency": "Monthly",
        "units": "Level",
        "popularity": 1
    },
    "ACTLISCOUMM42111": {
        "title": "Housing Inventory: Active Listing Count Month-Over-Month in Somerset County, PA",
        "start": "2017-07-01",
        "end": "2022-11-01",
        "frequency": "Monthly",
        "units": "Percent",
        "popularity": 1
    },
    "ACTLISCOUYY42111": {
        "title": "Housing Inventory: Active Listing Count Year-Over-Year in Somerset County, PA",
        "start": "2017-07-01",
        "end": "2022-11-01",
        "frequency": "Monthly",
        "units": "Percent",
        "popularity": 1
    },
    "ATNHPIUS42111A": {
        "title": "All-Transactions House Price Index for Somerset County, PA",
        "start": "1992-01-01",
        "end": "2021-01-01",
        "frequency": "Annual",
        "units": "Index 2000=100",
        "popularity": 1
    },
    "AVELISPRI42111": {
        "title": "Housing Inventory: Average Listing Price in Somerset County, PA",
        "start": "2016-07-01",
        "end": "2022-11-01",
        "frequency": "Monthly",
        "units": "U.S. Dollars",
        "popularity": 1
    },
    "AVELISPRIMM42111": {
        "title": "Housing Inventory: Average Listing Price Month-Over-Month in Somerset County, PA",
        "start": "2017-07-01",
        "end": "2022-11-01",
        "frequency": "Monthly",
        "units": "Percent",
        "popularity": 1
    },
    "AVELISPRIYY42111": {
        "title": "Housing Inventory: Average Listing Price Year-Over-Year in Somerset County, PA",
        "start": "2017-07-01",
        "end": "2022-11-01",
        "frequency": "Monthly",
        "units": "Percent",
        "popularity": 1
    },
    "B01002001E042111": {
        "title": "Estimate, Median Age by Sex, Total Population (5-year estimate) in Somerset County, PA",
        "start": "2009-01-01",
        "end": "2021-01-01",
        "frequency": "Annual",
        "units": "Years of Age",
        "popularity": 1
    },
    "B03002001E042111": {
        "title": "Population Estimate, Total (5-year estimate) in Somerset County, PA",
        "start": "2009-01-01",
        "end": "2021-01-01",
        "frequency": "Annual",
        "units": "Persons",
        "popularity": 1
    },
    "B03002002E042111": {
        "title": "Population Estimate, Total, Not Hispanic or Latino (5-year estimate) in Somerset County, PA",
        "start": "2009-01-01",
        "end": "2021-01-01",
        "frequency": "Annual",
        "units": "Persons",
        "popularity": 0
    },
    "B03002003E042111": {
        "title": "Population Estimate, Total, Not Hispanic or Latino, White Alone (5-year estimate) in Somerset County, PA",
        "start": "2009-01-01",
        "end": "2021-01-01",
        "frequency": "Annual",
        "units": "Persons",
        "popularity": 0
    },
    "B03002004E042111": {
        "title": "Population Estimate, Total, Not Hispanic or Latino, Black or African American Alone (5-year estimate) in Somerset County, PA",
        "start": "2009-01-01",
        "end": "2021-01-01",
        "frequency": "Annual",
        "units": "Persons",
        "popularity": 1
    },
    "B03002005E042111": {
        "title": "Population Estimate, Total, Not Hispanic or Latino, American Indian and Alaska Native Alone (5-year estimate) in Somerset County, PA",
        "start": "2009-01-01",
        "end": "2021-01-01",
        "frequency": "Annual",
        "units": "Persons",
        "popularity": 0
    },
    "B03002006E042111": {
        "title": "Population Estimate, Total, Not Hispanic or Latino, Asian Alone (5-year estimate) in Somerset County, PA",
        "start": "2009-01-01",
        "end": "2021-01-01",
        "frequency": "Annual",
        "units": "Persons",
        "popularity": 1
    },
    "B03002007E042111": {
        "title": "Population Estimate, Total, Not Hispanic or Latino, Native Hawaiian and Other Pacific Islander Alone (5-year estimate) in Somerset County, PA",
        "start": "2009-01-01",
        "end": "2021-01-01",
        "frequency": "Annual",
        "units": "Persons",
        "popularity": 0
    },
    "B03002008E042111": {
        "title": "Population Estimate, Total, Not Hispanic or Latino, Some Other Race Alone (5-year estimate) in Somerset County, PA",
        "start": "2009-01-01",
        "end": "2021-01-01",
        "frequency": "Annual",
        "units": "Persons",
        "popularity": 0
    },
    "B03002009E042111": {
        "title": "Population Estimate, Total, Not Hispanic or Latino, Two or More Races (5-year estimate) in Somerset County, PA",
        "start": "2009-01-01",
        "end": "2021-01-01",
        "frequency": "Annual",
        "units": "Persons",
        "popularity": 0
    },
    "B03002010E042111": {
        "title": "Population Estimate, Total, Not Hispanic or Latino, Two or More Races, Two Races Including Some Other Race (5-year estimate) in Somerset County, PA",
        "start": "2009-01-01",
        "end": "2021-01-01",
        "frequency": "Annual",
        "units": "Persons",
        "popularity": 0
    },
    "B03002011E042111": {
        "title": "Population Estimate, Total, Not Hispanic or Latino, Two or More Races, Two Races Excluding Some Other Race, and Three or More Races (5-year estimate) in Somerset County, PA",
        "start": "2009-01-01",
        "end": "2021-01-01",
        "frequency": "Annual",
        "units": "Persons",
        "popularity": 0
    },
    "B03002012E042111": {
        "title": "Population Estimate, Total, Hispanic or Latino (5-year estimate) in Somerset County, PA",
        "start": "2009-01-01",
        "end": "2021-01-01",
        "frequency": "Annual",
        "units": "Persons",
        "popularity": 1
    },
    "B03002013E042111": {
        "title": "Population Estimate, Total, Hispanic or Latino, White Alone (5-year estimate) in Somerset County, PA",
        "start": "2009-01-01",
        "end": "2021-01-01",
        "frequency": "Annual",
        "units": "Persons",
        "popularity": 1
    },
    "B03002014E042111": {
        "title": "Population Estimate, Total, Hispanic or Latino, Black or African American Alone (5-year estimate) in Somerset County, PA",
        "start": "2009-01-01",
        "end": "2021-01-01",
        "frequency": "Annual",
        "units": "Persons",
        "popularity": 1
    },
    "B03002015E042111": {
        "title": "Population Estimate, Total, Hispanic or Latino, American Indian and Alaska Native Alone (5-year estimate) in Somerset County, PA",
        "start": "2009-01-01",
        "end": "2021-01-01",
        "frequency": "Annual",
        "units": "Persons",
        "popularity": 0
    },
    "B03002016E042111": {
        "title": "Population Estimate, Total, Hispanic or Latino, Asian Alone (5-year estimate) in Somerset County, PA",
        "start": "2009-01-01",
        "end": "2021-01-01",
        "frequency": "Annual",
        "units": "Persons",
        "popularity": 0
    },
    "B03002017E042111": {
        "title": "Population Estimate, Total, Hispanic or Latino, Native Hawaiian and Other Pacific Islander Alone (5-year estimate) in Somerset County, PA",
        "start": "2009-01-01",
        "end": "2021-01-01",
        "frequency": "Annual",
        "units": "Persons",
        "popularity": 1
    },
    "B03002018E042111": {
        "title": "Population Estimate, Total, Hispanic or Latino, Some Other Race Alone (5-year estimate) in Somerset County, PA",
        "start": "2009-01-01",
        "end": "2021-01-01",
        "frequency": "Annual",
        "units": "Persons",
        "popularity": 0
    },
    "B03002019E042111": {
        "title": "Population Estimate, Total, Hispanic or Latino, Two or More Races (5-year estimate) in Somerset County, PA",
        "start": "2009-01-01",
        "end": "2021-01-01",
        "frequency": "Annual",
        "units": "Persons",
        "popularity": 0
    },
    "B03002020E042111": {
        "title": "Population Estimate, Total, Hispanic or Latino, Two or More Races, Two Races Including Some Other Race (5-year estimate) in Somerset County, PA",
        "start": "2009-01-01",
        "end": "2021-01-01",
        "frequency": "Annual",
        "units": "Persons",
        "popularity": 0
    },
    "B03002021E042111": {
        "title": "Population Estimate, Total, Hispanic or Latino, Two or More Races, Two Races Excluding Some Other Race, and Three or More Races (5-year estimate) in Somerset County, PA",
        "start": "2009-01-01",
        "end": "2021-01-01",
        "frequency": "Annual",
        "units": "Persons",
        "popularity": 0
    },
    "B080ACS042111": {
        "title": "Mean Commuting Time for Workers (5-year estimate) in Somerset County, PA",
        "start": "2009-01-01",
        "end": "2021-01-01",
        "frequency": "Annual",
        "units": "Minutes",
        "popularity": 1
    },
    "B14005DCYACS042111": {
        "title": "Disconnected Youth (5-year estimate) for Somerset County, PA",
        "start": "2009-01-01",
        "end": "2021-01-01",
        "frequency": "Annual",
        "units": "Percent",
        "popularity": 1
    },
    "BPPRIV042111": {
        "title": "New Private Housing Structures Authorized by Building Permits for Somerset County, PA",
        "start": "1990-01-01",
        "end": "2021-01-01",
        "frequency": "Annual",
        "units": "Units",
        "popularity": 1
    },
    "CBR42111PAA647NCEN": {
        "title": "SNAP Benefits Recipients in Somerset County, PA",
        "start": "1989-01-01",
        "end": "2020-01-01",
        "frequency": "Annual",
        "units": "Persons",
        "popularity": 1
    },
    "CDC20N2U042111": {
        "title": "Premature Death Rate for Somerset County, PA",
        "start": "1999-01-01",
        "end": "2020-01-01",
        "frequency": "Annual",
        "units": "Rate per 100,000",
        "popularity": 1
    },
    "CDC20N2UAA042111": {
        "title": "Age-Adjusted Premature Death Rate for Somerset County, PA",
        "start": "1999-01-01",
        "end": "2020-01-01",
        "frequency": "Annual",
        "units": "Rate per 100,000",
        "popularity": 1
    },
    "DESCCOUNTY42111": {
        "title": "Market Hotness: Demand Score in Somerset County, PA",
        "start": "2017-08-01",
        "end": "2022-11-01",
        "frequency": "Monthly",
        "units": "Score",
        "popularity": 1
    },
    "DMPCRATE042111": {
        "title": "Rate of Preventable Hospital Admissions (5-year estimate) in Somerset County, PA",
        "start": "2008-01-01",
        "end": "2015-01-01",
        "frequency": "Annual",
        "units": "Rate",
        "popularity": 0
    },
    "DP04ACS042111": {
        "title": "Burdened Households (5-year estimate) in Somerset County, PA",
        "start": "2010-01-01",
        "end": "2021-01-01",
        "frequency": "Annual",
        "units": "Percent",
        "popularity": 1
    },
    "ENU4211120510": {
        "title": "Number of Private Establishments for All Industries in Somerset County, PA",
        "start": "1990-01-01",
        "end": "2022-04-01",
        "frequency": "Quarterly",
        "units": "Establishments",
        "popularity": 1
    },
    "EQFXSUBPRIME042111": {
        "title": "Equifax Subprime Credit Population for Somerset County, PA",
        "start": "2014-04-01",
        "end": "2022-07-01",
        "frequency": "Quarterly",
        "units": "Percent",
        "popularity": 1
    },
    "GDPALL42111": {
        "title": "Gross Domestic Product: All Industries in Somerset County, PA",
        "start": "2001-01-01",
        "end": "2021-01-01",
        "frequency": "Annual",
        "units": "Thousands of U.S. Dollars",
        "popularity": 1
    },
    "GDPGOODS42111": {
        "title": "Gross Domestic Product: Private Goods-Producing Industries in Somerset County, PA",
        "start": "2001-01-01",
        "end": "2021-01-01",
        "frequency": "Annual",
        "units": "Thousands of U.S. Dollars",
        "popularity": 1
    },
    "GDPGOVT42111": {
        "title": "Gross Domestic Product: Government and Government Enterprises in Somerset County, PA",
        "start": "2001-01-01",
        "end": "2021-01-01",
        "frequency": "Annual",
        "units": "Thousands of U.S. Dollars",
        "popularity": 0
    },
    "GDPSERV42111": {
        "title": "Gross Domestic Product: Private Services-Providing Industries in Somerset County, PA",
        "start": "2001-01-01",
        "end": "2021-01-01",
        "frequency": "Annual",
        "units": "Thousands of U.S. Dollars",
        "popularity": 0
    },
    "HC01ESTVC1642111": {
        "title": "High School Graduate or Higher (5-year estimate) in Somerset County, PA",
        "start": "2010-01-01",
        "end": "2021-01-01",
        "frequency": "Annual",
        "units": "Percent",
        "popularity": 1
    },
    "HC01ESTVC1742111": {
        "title": "Bachelor's Degree or Higher (5-year estimate) in Somerset County, PA",
        "start": "2010-01-01",
        "end": "2021-01-01",
        "frequency": "Annual",
        "units": "Percent",
        "popularity": 1
    },
    "HORACOUNTY42111": {
        "title": "Market Hotness: Hotness Rank in Somerset County, PA",
        "start": "2017-08-01",
        "end": "2022-11-01",
        "frequency": "Monthly",
        "units": "Rank",
        "popularity": 1
    },
    "HORAMMCOUNTY42111": {
        "title": "Market Hotness: Hotness Rank in Somerset County, PA",
        "start": "2017-09-01",
        "end": "2022-11-01",
        "frequency": "Monthly",
        "units": "Rank Change",
        "popularity": 0
    },
    "HORAYYCOUNTY42111": {
        "title": "Market Hotness: Hotness Rank in Somerset County, PA",
        "start": "2018-08-01",
        "end": "2022-11-01",
        "frequency": "Monthly",
        "units": "Rank Change from Year Ago",
        "popularity": 1
    },
    "HOSCCOUNTY42111": {
        "title": "Market Hotness: Hotness Score in Somerset County, PA",
        "start": "2017-08-01",
        "end": "2022-11-01",
        "frequency": "Monthly",
        "units": "Score",
        "popularity": 0
    },
    "HOWNRATEACS042111": {
        "title": "Homeownership Rate (5-year estimate) for Somerset County, PA",
        "start": "2009-01-01",
        "end": "2021-01-01",
        "frequency": "Annual",
        "units": "Rate",
        "popularity": 1
    },
    "LAUCN421110000000003A": {
        "title": "Unemployment Rate in Somerset County, PA",
        "start": "1990-01-01",
        "end": "2021-01-01",
        "frequency": "Annual",
        "units": "Percent",
        "popularity": 1
    },
    "LAUCN421110000000004": {
        "title": "Unemployed Persons in Somerset County, PA",
        "start": "1990-01-01",
        "end": "2022-10-01",
        "frequency": "Monthly",
        "units": "Persons",
        "popularity": 1
    },
    "LAUCN421110000000004A": {
        "title": "Unemployed Persons in Somerset County, PA",
        "start": "1990-01-01",
        "end": "2021-01-01",
        "frequency": "Annual",
        "units": "Persons",
        "popularity": 0
    },
    "LAUCN421110000000005": {
        "title": "Employed Persons in Somerset County, PA",
        "start": "1990-01-01",
        "end": "2022-10-01",
        "frequency": "Monthly",
        "units": "Persons",
        "popularity": 1
    },
    "LAUCN421110000000005A": {
        "title": "Employed Persons in Somerset County, PA",
        "start": "1990-01-01",
        "end": "2021-01-01",
        "frequency": "Annual",
        "units": "Persons",
        "popularity": 1
    },
    "LAUCN421110000000006A": {
        "title": "Civilian Labor Force in Somerset County, PA",
        "start": "1990-01-01",
        "end": "2021-01-01",
        "frequency": "Annual",
        "units": "Persons",
        "popularity": 1
    },
    "LDPEPRMMCOUNTY42111": {
        "title": "Market Hotness: Listing Views per Property in Somerset County, PA",
        "start": "2017-09-01",
        "end": "2022-11-01",
        "frequency": "Monthly",
        "units": "Percent Change",
        "popularity": 1
    },
    "LDPEPRVSUSCOUNTY42111": {
        "title": "Market Hotness: Listing Views per Property Versus the United States in Somerset County, PA",
        "start": "2017-08-01",
        "end": "2022-11-01",
        "frequency": "Monthly",
        "units": "Ratio",
        "popularity": 1
    },
    "LDPEPRYYCOUNTY42111": {
        "title": "Market Hotness: Listing Views per Property in Somerset County, PA",
        "start": "2018-08-01",
        "end": "2022-11-01",
        "frequency": "Monthly",
        "units": "Percent Change from Year Ago",
        "popularity": 1
    },
    "MEDAONMACOUNTY42111": {
        "title": "Market Hotness: Median Days on Market in Somerset County, PA",
        "start": "2017-08-01",
        "end": "2022-11-01",
        "frequency": "Monthly",
        "units": "Days",
        "popularity": 1
    },
    "MEDAONMAMMCOUNTY42111": {
        "title": "Market Hotness: Median Days on Market in Somerset County, PA",
        "start": "2017-08-01",
        "end": "2022-11-01",
        "frequency": "Monthly",
        "units": "Percent Change",
        "popularity": 1
    },
    "MEDAONMAYYCOUNTY42111": {
        "title": "Market Hotness: Median Days on Market in Somerset County, PA",
        "start": "2017-08-01",
        "end": "2022-11-01",
        "frequency": "Monthly",
        "units": "Percent Change from Year Ago",
        "popularity": 1
    },
    "MEDDAYONMAR42111": {
        "title": "Housing Inventory: Median Days on Market in Somerset County, PA",
        "start": "2016-07-01",
        "end": "2022-11-01",
        "frequency": "Monthly",
        "units": "Level",
        "popularity": 1
    },
    "MEDDAYONMARMM42111": {
        "title": "Housing Inventory: Median Days on Market Month-Over-Month in Somerset County, PA",
        "start": "2017-07-01",
        "end": "2022-11-01",
        "frequency": "Monthly",
        "units": "Percent",
        "popularity": 1
    },
    "MEDDAYONMARYY42111": {
        "title": "Housing Inventory: Median Days on Market Year-Over-Year in Somerset County, PA",
        "start": "2017-07-01",
        "end": "2022-11-01",
        "frequency": "Monthly",
        "units": "Percent",
        "popularity": 1
    },
    "MEDLISPRI42111": {
        "title": "Housing Inventory: Median Listing Price in Somerset County, PA",
        "start": "2016-07-01",
        "end": "2022-11-01",
        "frequency": "Monthly",
        "units": "U.S. Dollars",
        "popularity": 1
    },
    "MEDLISPRIMM42111": {
        "title": "Housing Inventory: Median Listing Price Month-Over-Month in Somerset County, PA",
        "start": "2017-07-01",
        "end": "2022-11-01",
        "frequency": "Monthly",
        "units": "Percent",
        "popularity": 1
    },
    "MEDLISPRIPERSQUFEE42111": {
        "title": "Housing Inventory: Median Listing Price per Square Feet in Somerset County, PA",
        "start": "2016-07-01",
        "end": "2022-11-01",
        "frequency": "Monthly",
        "units": "U.S. Dollars",
        "popularity": 1
    },
    "MEDLISPRIPERSQUFEEMM42111": {
        "title": "Housing Inventory: Median Listing Price per Square Feet Month-Over-Month in Somerset County, PA",
        "start": "2017-07-01",
        "end": "2022-11-01",
        "frequency": "Monthly",
        "units": "Percent",
        "popularity": 1
    },
    "MEDLISPRIYY42111": {
        "title": "Housing Inventory: Median Listing Price Year-Over-Year in Somerset County, PA",
        "start": "2017-07-01",
        "end": "2022-11-01",
        "frequency": "Monthly",
        "units": "Percent",
        "popularity": 1
    },
    "MEDOMMDACOUNTY42111": {
        "title": "Market Hotness: Median Days on Market in Somerset County, PA",
        "start": "2017-08-01",
        "end": "2022-11-01",
        "frequency": "Monthly",
        "units": "Change",
        "popularity": 1
    },
    "MEDOVSUSCOUNTY42111": {
        "title": "Market Hotness: Median Days on Market Versus the United States in Somerset County, PA",
        "start": "2017-08-01",
        "end": "2022-11-01",
        "frequency": "Monthly",
        "units": "Ratio",
        "popularity": 0
    },
    "MEDOYYDACOUNTY42111": {
        "title": "Market Hotness: Median Days on Market Day in Somerset County, PA",
        "start": "2017-08-01",
        "end": "2022-11-01",
        "frequency": "Monthly",
        "units": "Change",
        "popularity": 1
    },
    "MEDSQUFEE42111": {
        "title": "Housing Inventory: Median Home Size in Square Feet in Somerset County, PA",
        "start": "2016-07-01",
        "end": "2022-11-01",
        "frequency": "Monthly",
        "units": "Level",
        "popularity": 1
    },
    "MEDSQUFEEMM42111": {
        "title": "Housing Inventory: Median Home Size in Square Feet Month-Over-Month in Somerset County, PA",
        "start": "2017-07-01",
        "end": "2022-11-01",
        "frequency": "Monthly",
        "units": "Percent",
        "popularity": 1
    },
    "MELIPRCOUNTY42111": {
        "title": "Market Hotness: Median Listing Price in Somerset County, PA",
        "start": "2017-08-01",
        "end": "2022-11-01",
        "frequency": "Monthly",
        "units": "U.S. Dollars",
        "popularity": 0
    },
    "MELIPRMMCOUNTY42111": {
        "title": "Market Hotness: Median Listing Price in Somerset County, PA",
        "start": "2017-08-01",
        "end": "2022-11-01",
        "frequency": "Monthly",
        "units": "Percent Change",
        "popularity": 1
    },
    "MELIPRVSUSCOUNTY42111": {
        "title": "Market Hotness: Median Listing Price Versus the United States in Somerset County, PA",
        "start": "2017-08-01",
        "end": "2022-11-01",
        "frequency": "Monthly",
        "units": "Ratio",
        "popularity": 1
    },
    "MELIPRYYCOUNTY42111": {
        "title": "Market Hotness: Median Listing Price in Somerset County, PA",
        "start": "2017-08-01",
        "end": "2022-11-01",
        "frequency": "Monthly",
        "units": "Percent Change from Year Ago",
        "popularity": 0
    },
    "MHICILBPA42111A052NCEN": {
        "title": "90% Confidence Interval Lower Bound of Estimate of Median Household Income for Somerset County, PA",
        "start": "1989-01-01",
        "end": "2021-01-01",
        "frequency": "Annual",
        "units": "Dollars",
        "popularity": 0
    },
    "MHICIUBPA42111A052NCEN": {
        "title": "90% Confidence Interval Upper Bound of Estimate of Median Household Income for Somerset County, PA",
        "start": "1989-01-01",
        "end": "2021-01-01",
        "frequency": "Annual",
        "units": "Dollars",
        "popularity": 0
    },
    "MHIPA42111A052NCEN": {
        "title": "Estimate of Median Household Income for Somerset County, PA",
        "start": "1989-01-01",
        "end": "2021-01-01",
        "frequency": "Annual",
        "units": "Dollars",
        "popularity": 1
    },
    "MWACL42111": {
        "title": "Estimated Mean Real Household Wages Adjusted by Cost of Living for Somerset County, PA",
        "start": "2016-01-01",
        "end": "2019-01-01",
        "frequency": "Annual",
        "units": "1999 U.S. Dollars",
        "popularity": 1
    },
    "NETMIGNACS042111": {
        "title": "Net County-to-County Migration Flow (5-year estimate) for Somerset County, PA",
        "start": "2009-01-01",
        "end": "2019-01-01",
        "frequency": "Annual",
        "units": "Persons",
        "popularity": 1
    },
    "NEWLISCOU42111": {
        "title": "Housing Inventory: New Listing Count in Somerset County, PA",
        "start": "2016-07-01",
        "end": "2022-11-01",
        "frequency": "Monthly",
        "units": "Level",
        "popularity": 1
    },
    "NEWLISCOUMM42111": {
        "title": "Housing Inventory: New Listing Count Month-Over-Month in Somerset County, PA",
        "start": "2017-07-01",
        "end": "2022-11-01",
        "frequency": "Monthly",
        "units": "Percent",
        "popularity": 1
    },
    "NEWLISCOUYY42111": {
        "title": "Housing Inventory: New Listing Count Year-Over-Year in Somerset County, PA",
        "start": "2017-07-01",
        "end": "2022-11-01",
        "frequency": "Monthly",
        "units": "Percent",
        "popularity": 1
    },
    "NIHHRACOUNTY42111": {
        "title": "Market Hotness: Nielsen Household Rank in Somerset County, PA",
        "start": "2017-08-01",
        "end": "2022-11-01",
        "frequency": "Monthly",
        "units": "Rank",
        "popularity": 0
    },
    "PASOME5LFN": {
        "title": "Civilian Labor Force in Somerset County, PA",
        "start": "1990-01-01",
        "end": "2022-10-01",
        "frequency": "Monthly",
        "units": "Persons",
        "popularity": 1
    },
    "PASOME5POP": {
        "title": "Resident Population in Somerset County, PA",
        "start": "1970-01-01",
        "end": "2021-01-01",
        "frequency": "Annual",
        "units": "Thousands of Persons",
        "popularity": 1
    },
    "PASOME5URN": {
        "title": "Unemployment Rate in Somerset County, PA",
        "start": "1990-01-01",
        "end": "2022-10-01",
        "frequency": "Monthly",
        "units": "Percent",
        "popularity": 2
    },
    "PATENTCOUNTY42111": {
        "title": "U.S. Granted Utility Patents Originating in Somerset County, PA",
        "start": "2000-01-01",
        "end": "2015-01-01",
        "frequency": "Annual",
        "units": "Number",
        "popularity": 0
    },
    "PCPI42111": {
        "title": "Per Capita Personal Income in Somerset County, PA",
        "start": "1969-01-01",
        "end": "2021-01-01",
        "frequency": "Annual",
        "units": "Dollars",
        "popularity": 1
    },
    "PE5T17PA42111A647NCEN": {
        "title": "Estimate of Related Children Age 5-17 in Families in Poverty for Somerset County, PA",
        "start": "1989-01-01",
        "end": "2021-01-01",
        "frequency": "Annual",
        "units": "Persons",
        "popularity": 0
    },
    "PEAAPA42111A647NCEN": {
        "title": "Estimate of People of All Ages in Poverty in Somerset County, PA",
        "start": "1989-01-01",
        "end": "2021-01-01",
        "frequency": "Annual",
        "units": "Persons",
        "popularity": 1
    },
    "PECILB5T17PA42111A647NCEN": {
        "title": "90% Confidence Interval Lower Bound of Estimate of Related Children Age 5-17 in Families in Poverty for Somerset County, PA",
        "start": "1989-01-01",
        "end": "2021-01-01",
        "frequency": "Annual",
        "units": "Persons",
        "popularity": 0
    },
    "PECILBAAPA42111A647NCEN": {
        "title": "90% Confidence Interval Lower Bound of Estimate of People of All Ages in Poverty for Somerset County, PA",
        "start": "1989-01-01",
        "end": "2021-01-01",
        "frequency": "Annual",
        "units": "Persons",
        "popularity": 0
    },
    "PECILBU18PA42111A647NCEN": {
        "title": "90% Confidence Interval Lower Bound of Estimate of People Age 0-17 in Poverty for Somerset County, PA",
        "start": "1989-01-01",
        "end": "2021-01-01",
        "frequency": "Annual",
        "units": "Persons",
        "popularity": 0
    },
    "PECIUB5T17PA42111A647NCEN": {
        "title": "90% Confidence Interval Upper Bound of Estimate of Related Children Age 5-17 in Families in Poverty for Somerset County, PA",
        "start": "1989-01-01",
        "end": "2021-01-01",
        "frequency": "Annual",
        "units": "Persons",
        "popularity": 0
    },
    "PECIUBAAPA42111A647NCEN": {
        "title": "90% Confidence Interval Upper Bound of Estimate of People of All Ages in Poverty for Somerset County, PA",
        "start": "1989-01-01",
        "end": "2021-01-01",
        "frequency": "Annual",
        "units": "Persons",
        "popularity": 0
    },
    "PECIUBU18PA42111A647NCEN": {
        "title": "90% Confidence Interval Upper Bound of Estimate of People Age 0-17 in Poverty for Somerset County, PA",
        "start": "1989-01-01",
        "end": "2021-01-01",
        "frequency": "Annual",
        "units": "Persons",
        "popularity": 0
    },
    "PENLISCOU42111": {
        "title": "Housing Inventory: Pending Listing Count in Somerset County, PA",
        "start": "2016-07-01",
        "end": "2022-11-01",
        "frequency": "Monthly",
        "units": "Level",
        "popularity": 1
    },
    "PENLISCOUMM42111": {
        "title": "Housing Inventory: Pending Listing Count Month-Over-Month in Somerset County, PA",
        "start": "2017-07-01",
        "end": "2022-11-01",
        "frequency": "Monthly",
        "units": "Percent",
        "popularity": 1
    },
    "PENLISCOUYY42111": {
        "title": "Housing Inventory: Pending Listing Count Year-Over-Year in Somerset County, PA",
        "start": "2017-07-01",
        "end": "2022-11-01",
        "frequency": "Monthly",
        "units": "Percent",
        "popularity": 1
    },
    "PENRAT42111": {
        "title": "Housing Inventory: Pending Ratio in Somerset County, PA",
        "start": "2016-07-01",
        "end": "2022-11-01",
        "frequency": "Monthly",
        "units": "Ratio",
        "popularity": 1
    },
    "PENRATMM42111": {
        "title": "Housing Inventory: Pending Ratio Month-Over-Month in Somerset County, PA",
        "start": "2017-07-01",
        "end": "2022-11-01",
        "frequency": "Monthly",
        "units": "Ratio",
        "popularity": 1
    },
    "PENRATYY42111": {
        "title": "Housing Inventory: Pending Ratio Year-Over-Year in Somerset County, PA",
        "start": "2017-07-01",
        "end": "2022-11-01",
        "frequency": "Monthly",
        "units": "Ratio",
        "popularity": 1
    },
    "PEU18PA42111A647NCEN": {
        "title": "Estimate of People Age 0-17 in Poverty in Somerset County, PA",
        "start": "1989-01-01",
        "end": "2021-01-01",
        "frequency": "Annual",
        "units": "Persons",
        "popularity": 0
    },
    "PI42111": {
        "title": "Personal Income in Somerset County, PA",
        "start": "1969-01-01",
        "end": "2021-01-01",
        "frequency": "Annual",
        "units": "Thousands of Dollars",
        "popularity": 1
    },
    "PP5T17PA42111A156NCEN": {
        "title": "Estimated Percent of Related Children Age 5-17 in Families in Poverty for Somerset County, PA",
        "start": "1989-01-01",
        "end": "2021-01-01",
        "frequency": "Annual",
        "units": "Percent",
        "popularity": 0
    },
    "PPAAPA42111A156NCEN": {
        "title": "Estimated Percent of People of All Ages in Poverty for Somerset County, PA",
        "start": "1989-01-01",
        "end": "2021-01-01",
        "frequency": "Annual",
        "units": "Percent",
        "popularity": 1
    },
    "PPCILB5T17PA42111A156NCEN": {
        "title": "90% Confidence Interval Lower Bound of Estimate of Percent of Related Children Age 5-17 in Families in Poverty for Somerset County, PA",
        "start": "1989-01-01",
        "end": "2021-01-01",
        "frequency": "Annual",
        "units": "Percent",
        "popularity": 0
    },
    "PPCILBAAPA42111A156NCEN": {
        "title": "90% Confidence Interval Lower Bound of Estimate of Percent of People of All Ages in Poverty for Somerset County, PA",
        "start": "1989-01-01",
        "end": "2021-01-01",
        "frequency": "Annual",
        "units": "Percent",
        "popularity": 1
    },
    "PPCILBU18PA42111A156NCEN": {
        "title": "90% Confidence Interval Lower Bound of Estimate of Percent of People Age 0-17 in Poverty for Somerset County, PA",
        "start": "1989-01-01",
        "end": "2021-01-01",
        "frequency": "Annual",
        "units": "Percent",
        "popularity": 0
    },
    "PPCIUB5T17PA42111A156NCEN": {
        "title": "90% Confidence Interval Upper Bound of Estimate of Percent of Related Children Age 5-17 in Families in Poverty for Somerset County, PA",
        "start": "1989-01-01",
        "end": "2021-01-01",
        "frequency": "Annual",
        "units": "Percent",
        "popularity": 0
    },
    "PPCIUBAAPA42111A156NCEN": {
        "title": "90% Confidence Interval Upper Bound of Estimate of Percent of People of All Ages in Poverty for Somerset County, PA",
        "start": "1989-01-01",
        "end": "2021-01-01",
        "frequency": "Annual",
        "units": "Percent",
        "popularity": 0
    },
    "PPCIUBU18PA42111A156NCEN": {
        "title": "90% Confidence Interval Upper Bound of Estimate of Percent of People Age 0-17 in Poverty for Somerset County, PA",
        "start": "1989-01-01",
        "end": "2021-01-01",
        "frequency": "Annual",
        "units": "Percent",
        "popularity": 0
    },
    "PPU18PA42111A156NCEN": {
        "title": "Estimated Percent of People Age 0-17 in Poverty for Somerset County, PA",
        "start": "1989-01-01",
        "end": "2021-01-01",
        "frequency": "Annual",
        "units": "Percent",
        "popularity": 0
    },
    "PRIINCCOU42111": {
        "title": "Housing Inventory: Price Increased Count in Somerset County, PA",
        "start": "2016-07-01",
        "end": "2022-11-01",
        "frequency": "Monthly",
        "units": "Level",
        "popularity": 0
    },
    "PRIINCCOUMM42111": {
        "title": "Housing Inventory: Price Increased Count Month-Over-Month in Somerset County, PA",
        "start": "2017-07-01",
        "end": "2022-04-01",
        "frequency": "Monthly",
        "units": "Percent",
        "popularity": 0
    },
    "PRIINCCOUYY42111": {
        "title": "Housing Inventory: Price Increased Count Year-Over-Year in Somerset County, PA",
        "start": "2018-01-01",
        "end": "2022-09-01",
        "frequency": "Monthly",
        "units": "Percent",
        "popularity": 1
    },
    "PRIREDCOU42111": {
        "title": "Housing Inventory: Price Reduced Count in Somerset County, PA",
        "start": "2016-07-01",
        "end": "2022-11-01",
        "frequency": "Monthly",
        "units": "Level",
        "popularity": 1
    },
    "PRIREDCOUMM42111": {
        "title": "Housing Inventory: Price Reduced Count Month-Over-Month in Somerset County, PA",
        "start": "2017-07-01",
        "end": "2022-11-01",
        "frequency": "Monthly",
        "units": "Percent",
        "popularity": 0
    },
    "PRIREDCOUYY42111": {
        "title": "Housing Inventory: Price Reduced Count Year-Over-Year in Somerset County, PA",
        "start": "2017-07-01",
        "end": "2022-11-01",
        "frequency": "Monthly",
        "units": "Percent",
        "popularity": 1
    },
    "PUA0T17PA42111A647NCEN": {
        "title": "Poverty Universe, Age 0-17 for Somerset County, PA",
        "start": "1998-01-01",
        "end": "2021-01-01",
        "frequency": "Annual",
        "units": "Persons",
        "popularity": 0
    },
    "PUA5T17RPA42111A647NCEN": {
        "title": "Poverty Universe, Age 5-17 related for Somerset County, PA",
        "start": "1998-01-01",
        "end": "2021-01-01",
        "frequency": "Annual",
        "units": "Persons",
        "popularity": 0
    },
    "PUAAPA42111A647NCEN": {
        "title": "Poverty Universe, All Ages for Somerset County, PA",
        "start": "1998-01-01",
        "end": "2021-01-01",
        "frequency": "Annual",
        "units": "Persons",
        "popularity": 1
    },
    "RACEDISPARITY042111": {
        "title": "White to Non-White Racial Dissimilarity (5-year estimate) Index for Somerset County, PA",
        "start": "2009-01-01",
        "end": "2021-01-01",
        "frequency": "Annual",
        "units": "Percent",
        "popularity": 1
    },
    "REALGDPALL42111": {
        "title": "Real Gross Domestic Product: All Industries in Somerset County, PA",
        "start": "2001-01-01",
        "end": "2021-01-01",
        "frequency": "Annual",
        "units": "Thousands of Chained 2012 U.S. Dollars",
        "popularity": 1
    },
    "REALGDPGOODS42111": {
        "title": "Real Gross Domestic Product: Private Goods-Producing Industries in Somerset County, PA",
        "start": "2001-01-01",
        "end": "2021-01-01",
        "frequency": "Annual",
        "units": "Thousands of Chained 2012 U.S. Dollars",
        "popularity": 0
    },
    "REALGDPGOVT42111": {
        "title": "Real Gross Domestic Product: Government and Government Enterprises in Somerset County, PA",
        "start": "2001-01-01",
        "end": "2021-01-01",
        "frequency": "Annual",
        "units": "Thousands of Chained 2012 U.S. Dollars",
        "popularity": 0
    },
    "REALGDPSERV42111": {
        "title": "Real Gross Domestic Product: Private Services-Providing Industries in Somerset County, PA",
        "start": "2001-01-01",
        "end": "2021-01-01",
        "frequency": "Annual",
        "units": "Thousands of Chained 2012 U.S. Dollars",
        "popularity": 0
    },
    "S1101SPHOUSE042111": {
        "title": "Single-Parent Households with Children as a Percentage of Households with Children (5-year estimate) in Somerset County, PA",
        "start": "2009-01-01",
        "end": "2021-01-01",
        "frequency": "Annual",
        "units": "Percent",
        "popularity": 1
    },
    "S1501ACSTOTAL042111": {
        "title": "People 25 Years and Over Who Have Completed an Associate's Degree or Higher (5-year estimate) in Somerset County, PA",
        "start": "2009-01-01",
        "end": "2021-01-01",
        "frequency": "Annual",
        "units": "Percent",
        "popularity": 0
    },
    "S1701ACS042111": {
        "title": "Percent of Population Below the Poverty Level (5-year estimate) in Somerset County, PA",
        "start": "2012-01-01",
        "end": "2021-01-01",
        "frequency": "Annual",
        "units": "Percent",
        "popularity": 1
    },
    "SUSCCOUNTY42111": {
        "title": "Market Hotness: Supply Score in Somerset County, PA",
        "start": "2017-08-01",
        "end": "2022-11-01",
        "frequency": "Monthly",
        "units": "Score",
        "popularity": 0
    },
    "TOTLISCOU42111": {
        "title": "Housing Inventory: Total Listing Count in Somerset County, PA",
        "start": "2016-07-01",
        "end": "2022-11-01",
        "frequency": "Monthly",
        "units": "Level",
        "popularity": 1
    },
    "TOTLISCOUMM42111": {
        "title": "Housing Inventory: Total Listing Count Month-Over-Month in Somerset County, PA",
        "start": "2017-07-01",
        "end": "2022-11-01",
        "frequency": "Monthly",
        "units": "Percent",
        "popularity": 1
    },
    "TOTLISCOUYY42111": {
        "title": "Housing Inventory: Total Listing Count Year-Over-Year in Somerset County, PA",
        "start": "2017-07-01",
        "end": "2022-11-01",
        "frequency": "Monthly",
        "units": "Percent",
        "popularity": 1
    },
    "USPTOISSUED042111": {
        "title": "New Patent Assignments in Somerset County, PA",
        "start": "1981-12-01",
        "end": "2021-03-01",
        "frequency": "Monthly",
        "units": "Patents",
        "popularity": 1
    }
}